src/alu.v
//=====================================================================
// File        : alu.v
// Author      : Prabhat Pandey
// Created On  : 25-Jan-2026
// Project     : RV32I Single-Cycle 32-bit RISC-V Processor
// Module Name : alu
// Description :
//   This module implements the Arithmetic Logic Unit (ALU) for an
//   RV32I single-cycle RISC-V processor.
//
// Supported Operations (RV32I):
//   - ADD, SUB
//   - AND, OR, XOR
//   - SLL (logical left shift)
//   - SRL (logical right shift)
//   - SRA (arithmetic right shift)
//   - SLT  (signed compare)
//   - SLTU (unsigned compare)
//
// Interface:
//   Inputs:
//     - A          : 32-bit operand A
//     - B          : 32-bit operand B
//     - ALUControl : 4-bit ALU operation selector
//
//   Outputs:
//     - Result     : 32-bit ALU output
//     - Carry      : carry-out (valid for ADD/SUB mainly)
//     - OverFlow   : signed overflow flag (valid for ADD/SUB)
//     - Zero       : 1 if Result == 0
//     - Negative   : MSB of Result (Result[31])
//
// Notes:
//   - Carry for subtraction is implemented using A + (~B + 1).
//     This means:
//       Carry = 1 indicates "no borrow"
//       Carry = 0 indicates "borrow occurred"
//   - Overflow is computed using signed arithmetic rules.
//
// ALUControl Encoding (4-bit):
//   0000 : ADD
//   0001 : SUB
//   0010 : AND
//   0011 : OR
//   0100 : XOR
//   0101 : SLT   (signed)
//   0110 : SLTU  (unsigned)
//   0111 : SLL
//   1000 : SRL
//   1001 : SRA
//
// Revision History:
//   - 13-Feb-2026 : Updated Functionality
//   - 25-Jan-2026 : Initial version
//=====================================================================

module alu (
    input  wire [31:0] A,           // Operand A
    input  wire [31:0] B,           // Operand B
    input  wire [3:0]  ALUControl,  // ALU operation selector
    output reg  [31:0] Result,      // ALU result
    output reg         Carry,       // Carry-out (ADD/SUB)
    output reg         OverFlow,    // Signed overflow (ADD/SUB)
    output wire        Zero,        // Result == 0
    output wire        Negative     // Result[31]
);

    //=================================================================
    // Internal Signals for ADD/SUB
    //=================================================================
    // We use a 33-bit sum to capture carry-out.
    //=================================================================
    reg  [32:0] sum_ext;
    wire [31:0] B_sub;

    // For subtraction: use two's complement of B
    assign B_sub = ~B + 32'd1;

    //=================================================================
    // Combinational ALU
    //=================================================================
    always @(*) begin

        // Default outputs
        Result   = 32'h0000_0000;
        Carry    = 1'b0;
        OverFlow = 1'b0;
        sum_ext  = 33'd0;

        case (ALUControl)

            // ------------------------------------------------------
            // ADD
            // ------------------------------------------------------
            4'b0000: begin
                sum_ext = {1'b0, A} + {1'b0, B};
                Result  = sum_ext[31:0];
                Carry   = sum_ext[32];

                // Signed overflow:
                // if A and B have same sign, but Result has different sign
                OverFlow = (~(A[31] ^ B[31])) & (A[31] ^ Result[31]);
            end

            // ------------------------------------------------------
            // SUB
            // ------------------------------------------------------
            4'b0001: begin
                sum_ext = {1'b0, A} + {1'b0, B_sub};
                Result  = sum_ext[31:0];
                Carry   = sum_ext[32]; // 1 means no borrow

                // Signed overflow for subtraction:
                // if A and B have different sign, and Result sign differs from A
                OverFlow = (A[31] ^ B[31]) & (A[31] ^ Result[31]);
            end

            // ------------------------------------------------------
            // AND
            // ------------------------------------------------------
            4'b0010: begin
                Result = A & B;
            end

            // ------------------------------------------------------
            // OR
            // ------------------------------------------------------
            4'b0011: begin
                Result = A | B;
            end

            // ------------------------------------------------------
            // XOR
            // ------------------------------------------------------
            4'b0100: begin
                Result = A ^ B;
            end

            // ------------------------------------------------------
            // SLT (signed)
            // ------------------------------------------------------
            4'b0101: begin
                Result = ($signed(A) < $signed(B)) ? 32'd1 : 32'd0;
            end

            // ------------------------------------------------------
            // SLTU (unsigned)
            // ------------------------------------------------------
            4'b0110: begin
                Result = (A < B) ? 32'd1 : 32'd0;
            end

            // ------------------------------------------------------
            // SLL (logical left shift)
            // Only lower 5 bits of B used for shift amount (RV32 rule)
            // ------------------------------------------------------
            4'b0111: begin
                Result = A << B[4:0];
            end

            // ------------------------------------------------------
            // SRL (logical right shift)
            // ------------------------------------------------------
            4'b1000: begin
                Result = A >> B[4:0];
            end

            // ------------------------------------------------------
            // SRA (arithmetic right shift)
            // ------------------------------------------------------
            4'b1001: begin
                Result = $signed(A) >>> B[4:0];
            end

            // ------------------------------------------------------
            // Default
            // ------------------------------------------------------
            default: begin
                Result   = 32'h0000_0000;
                Carry    = 1'b0;
                OverFlow = 1'b0;
            end

        endcase
    end

    //=================================================================
    // Flags
    //=================================================================
    assign Zero     = (Result == 32'h0000_0000);
    assign Negative = Result[31];

endmodule

RTL_Verification/tb_alu.v
//=====================================================================
// File        : tb_alu.v
// Author      : Prabhat Pandey
// Created On  : 15-Feb-2026
// Project     : RV32I Single-Cycle 32-bit RISC-V Processor
// Testbench   : tb_alu
// Description :
//   Fully self-checking testbench for alu.v
//
// ALUControl Encoding (must match alu.v):
//   0000 : ADD
//   0001 : SUB
//   0010 : AND
//   0011 : OR
//   0100 : XOR
//   0101 : SLT   (signed)
//   0110 : SLTU  (unsigned)
//   0111 : SLL
//   1000 : SRL
//   1001 : SRA
//
// Verification Features:
//   - Fully self-checking
//   - Input print
//   - Expected output print
//   - Actual output print
//   - PASS/FAIL per test case
//   - Global counters
//   - Final verification summary report
//
// Run Commands:
//   iverilog -o ./Verification_Results/result_tb_alu ./src/alu.v ./RTL_Verification/tb_alu.v
//   vvp ./Verification_Results/result_tb_alu
//=====================================================================

`timescale 1ns/1ps

module tb_alu;

    //=============================================================
    // Testbench Parameters
    //=============================================================
    localparam integer TEST_DELAY = 10; // ns between tests for waveform visibility

    //=============================================================
    // DUT Signals
    //=============================================================
    reg  [31:0] A;
    reg  [31:0] B;
    reg  [3:0]  ALUControl;

    wire [31:0] Result;
    wire        Carry;
    wire        OverFlow;
    wire        Zero;
    wire        Negative;

    //=============================================================
    // Instantiate DUT
    //=============================================================
    alu dut (
        .A          (A),
        .B          (B),
        .ALUControl (ALUControl),
        .Result     (Result),
        .Carry      (Carry),
        .OverFlow   (OverFlow),
        .Zero       (Zero),
        .Negative   (Negative)
    );

    //=============================================================
    // Global Counters
    //=============================================================
    integer total_tests;
    integer passed_tests;
    integer failed_tests;

    //=============================================================
    // VCD Dump (for GTKWave)
    //=============================================================
    initial begin
        $dumpfile("tb_alu.vcd");
        $dumpvars(0, tb_alu);
    end

    //=============================================================
    // Task: Divider
    //=============================================================
    task print_divider;
        begin
            $display("----------------------------------------------------------------");
        end
    endtask

    //=============================================================
    // Task: Run One ALU Test
    //=============================================================
    task run_test;
        input [8*60:1] test_name;
        input [31:0]   A_in;
        input [31:0]   B_in;
        input [3:0]    ctrl_in;

        input [31:0]   exp_result;
        input          exp_carry;
        input          exp_overflow;
        input          exp_zero;
        input          exp_negative;

        reg [31:0] got_result;
        reg        got_carry;
        reg        got_overflow;
        reg        got_zero;
        reg        got_negative;

        begin
            total_tests = total_tests + 1;

            print_divider();
            $display("TEST : %s", test_name);

            // Apply inputs
            A          = A_in;
            B          = B_in;
            ALUControl = ctrl_in;

            #2; // combinational settle

            // Sample outputs
            got_result   = Result;
            got_carry    = Carry;
            got_overflow = OverFlow;
            got_zero     = Zero;
            got_negative = Negative;

            // Print Inputs
            $display("Inputs:");
            $display("   A          = %08h", A_in);
            $display("   B          = %08h", B_in);
            $display("   ALUControl = %04b", ctrl_in);

            // Print Expected
            $display("");
            $display("Expected:");
            $display("   Result     = %08h", exp_result);
            $display("   Carry      = %0d", exp_carry);
            $display("   OverFlow   = %0d", exp_overflow);
            $display("   Zero       = %0d", exp_zero);
            $display("   Negative   = %0d", exp_negative);

            // Print Got
            $display("");
            $display("Got:");
            $display("   Result     = %08h", got_result);
            $display("   Carry      = %0d", got_carry);
            $display("   OverFlow   = %0d", got_overflow);
            $display("   Zero       = %0d", got_zero);
            $display("   Negative   = %0d", got_negative);

            // Compare
            if ((got_result   === exp_result)   &&
                (got_carry    === exp_carry)    &&
                (got_overflow === exp_overflow) &&
                (got_zero     === exp_zero)     &&
                (got_negative === exp_negative)) begin

                passed_tests = passed_tests + 1;
                $display("STATUS: PASS");
            end
            else begin
                failed_tests = failed_tests + 1;
                $display("STATUS: FAIL");
            end

            print_divider();
            $display("");

            #(TEST_DELAY);
        end
    endtask

    //=============================================================
    // Main Test Sequence
    //=============================================================
    initial begin

        // Init counters
        total_tests  = 0;
        passed_tests = 0;
        failed_tests = 0;

        // Init inputs
        A          = 32'h0000_0000;
        B          = 32'h0000_0000;
        ALUControl = 4'b0000;

        $display("====================================================");
        $display(" ALU VERIFICATION STARTED — Author: Prabhat Pandey");
        $display("====================================================");
        $display("");

        //=========================================================
        // ADD TESTS (0000)
        //=========================================================
        run_test("ADD basic",
                 32'h0000_0005, 32'h0000_0007, 4'b0000,
                 32'h0000_000C, 1'b0, 1'b0, 1'b0, 1'b0);

        run_test("ADD wrap",
                 32'hFFFF_FFFF, 32'h0000_0001, 4'b0000,
                 32'h0000_0000, 1'b1, 1'b0, 1'b1, 1'b0);

        run_test("ADD signed overflow",
                 32'h7FFF_FFFF, 32'h0000_0001, 4'b0000,
                 32'h8000_0000, 1'b0, 1'b1, 1'b0, 1'b1);

        run_test("ADD negative + negative overflow",
                 32'h8000_0000, 32'h8000_0000, 4'b0000,
                 32'h0000_0000, 1'b1, 1'b1, 1'b1, 1'b0);

        //=========================================================
        // SUB TESTS (0001)
        //=========================================================
        run_test("SUB basic",
                 32'h0000_0014, 32'h0000_0007, 4'b0001,
                 32'h0000_000D, 1'b1, 1'b0, 1'b0, 1'b0);

        run_test("SUB negative result",
                 32'h0000_0007, 32'h0000_0014, 4'b0001,
                 32'hFFFF_FFF3, 1'b0, 1'b0, 1'b0, 1'b1);

        run_test("SUB signed overflow",
                 32'h8000_0000, 32'h0000_0001, 4'b0001,
                 32'h7FFF_FFFF, 1'b1, 1'b1, 1'b0, 1'b0);

        //=========================================================
        // AND TESTS (0010)
        //=========================================================
        run_test("AND test",
                 32'hF0F0_F0F0, 32'h0FF0_0FF0, 4'b0010,
                 32'h00F0_00F0, 1'b0, 1'b0, 1'b0, 1'b0);

        //=========================================================
        // OR TESTS (0011)
        //=========================================================
        run_test("OR test",
                 32'hA5A5_A5A5, 32'h0F0F_0F0F, 4'b0011,
                 32'hAFAF_AFAF, 1'b0, 1'b0, 1'b0, 1'b1);

        //=========================================================
        // XOR TESTS (0100)
        //=========================================================
        run_test("XOR test",
                 32'hAAAA_AAAA, 32'h5555_5555, 4'b0100,
                 32'hFFFF_FFFF, 1'b0, 1'b0, 1'b0, 1'b1);

        //=========================================================
        // SLT TESTS (0101)
        //=========================================================
        run_test("SLT -5 < 5",
                 32'hFFFF_FFFB, 32'h0000_0005, 4'b0101,
                 32'h0000_0001, 1'b0, 1'b0, 1'b0, 1'b0);

        run_test("SLT 5 < -5",
                 32'h0000_0005, 32'hFFFF_FFFB, 4'b0101,
                 32'h0000_0000, 1'b0, 1'b0, 1'b1, 1'b0);

        run_test("SLT min negative < 0",
                 32'h8000_0000, 32'h0000_0000, 4'b0101,
                 32'h0000_0001, 1'b0, 1'b0, 1'b0, 1'b0);

        //=========================================================
        // SLTU TESTS (0110)
        //=========================================================
        run_test("SLTU 1 < max",
                 32'h0000_0001, 32'hFFFF_FFFF, 4'b0110,
                 32'h0000_0001, 1'b0, 1'b0, 1'b0, 1'b0);

        run_test("SLTU max < 1",
                 32'hFFFF_FFFF, 32'h0000_0001, 4'b0110,
                 32'h0000_0000, 1'b0, 1'b0, 1'b1, 1'b0);

        run_test("SLTU unsigned compare",
                 32'h8000_0000, 32'h7FFF_FFFF, 4'b0110,
                 32'h0000_0000, 1'b0, 1'b0, 1'b1, 1'b0);

        //=========================================================
        // SLL TESTS (0111)
        //=========================================================
        run_test("SLL 1<<5",
                 32'h0000_0001, 32'h0000_0005, 4'b0111,
                 32'h0000_0020, 1'b0, 1'b0, 1'b0, 1'b0);

        run_test("SLL overflow shift",
                 32'hF000_0000, 32'h0000_0004, 4'b0111,
                 32'h0000_0000, 1'b0, 1'b0, 1'b1, 1'b0);

        //=========================================================
        // SRL TESTS (1000)
        //=========================================================
        run_test("SRL logical right",
                 32'h8000_0000, 32'h0000_001F, 4'b1000,
                 32'h0000_0001, 1'b0, 1'b0, 1'b0, 1'b0);

        run_test("SRL shift",
                 32'hFFFF_FFFF, 32'h0000_0004, 4'b1000,
                 32'h0FFF_FFFF, 1'b0, 1'b0, 1'b0, 1'b0);

        //=========================================================
        // SRA TESTS (1001)
        //=========================================================
        run_test("SRA arithmetic",
                 32'hFFFF_FFFF, 32'h0000_0004, 4'b1001,
                 32'hFFFF_FFFF, 1'b0, 1'b0, 1'b0, 1'b1);

        run_test("SRA sign extend",
                 32'h8000_0000, 32'h0000_001F, 4'b1001,
                 32'hFFFF_FFFF, 1'b0, 1'b0, 1'b0, 1'b1);

        //=========================================================
        // Zero flag test (ADD)
        //=========================================================
        run_test("Zero flag test",
                 32'h0000_000A, 32'hFFFF_FFF6, 4'b0000,
                 32'h0000_0000, 1'b1, 1'b0, 1'b1, 1'b0);

        //=========================================================
        // Final Summary Report
        //=========================================================
        $display("====================================================");
        $display(" ALU VERIFICATION REPORT");
        $display("====================================================");
        $display("   Total Tests   : %0d", total_tests);
        $display("   Passed        : %0d", passed_tests);
        $display("   Failed        : %0d", failed_tests);
        $display("====================================================");

        if (failed_tests == 0) begin
            $display("STATUS: ALL TESTS PASSED");
        end
        else begin
            $display("STATUS: SOME TESTS FAILED");
        end

        $display("====================================================");
        $display("");

        $finish;
    end

endmodule

Verification_Results/tb_alu.vcd
$date
	Wed Feb 25 22:41:49 2026
$end
$version
	Icarus Verilog
$end
$timescale
	1ps
$end
$scope module tb_alu $end
$var wire 1 ! Zero $end
$var wire 32 " Result [31:0] $end
$var wire 1 # OverFlow $end
$var wire 1 $ Negative $end
$var wire 1 % Carry $end
$var parameter 32 & TEST_DELAY $end
$var reg 32 ' A [31:0] $end
$var reg 4 ( ALUControl [3:0] $end
$var reg 32 ) B [31:0] $end
$var integer 32 * failed_tests [31:0] $end
$var integer 32 + passed_tests [31:0] $end
$var integer 32 , total_tests [31:0] $end
$scope module dut $end
$var wire 32 - A [31:0] $end
$var wire 4 . ALUControl [3:0] $end
$var wire 32 / B [31:0] $end
$var wire 1 ! Zero $end
$var wire 1 $ Negative $end
$var wire 32 0 B_sub [31:0] $end
$var reg 1 % Carry $end
$var reg 1 # OverFlow $end
$var reg 32 1 Result [31:0] $end
$var reg 33 2 sum_ext [32:0] $end
$upscope $end
$scope task print_divider $end
$upscope $end
$scope task run_test $end
$var reg 32 3 A_in [31:0] $end
$var reg 32 4 B_in [31:0] $end
$var reg 4 5 ctrl_in [3:0] $end
$var reg 1 6 exp_carry $end
$var reg 1 7 exp_negative $end
$var reg 1 8 exp_overflow $end
$var reg 32 9 exp_result [31:0] $end
$var reg 1 : exp_zero $end
$var reg 1 ; got_carry $end
$var reg 1 < got_negative $end
$var reg 1 = got_overflow $end
$var reg 32 > got_result [31:0] $end
$var reg 1 ? got_zero $end
$var reg 480 @ test_name [480:1] $end
$upscope $end
$upscope $end
$enddefinitions $end
$comment Show the parameter values. $end
$dumpall
b1010 &
$end
#0
$dumpvars
b10000010100010001000100001000000110001001100001011100110110100101100011 @
x?
bx >
x=
x<
x;
0:
b1100 9
08
07
06
b0 5
b111 4
b101 3
b1100 2
b1100 1
b11111111111111111111111111111001 0
b111 /
b0 .
b101 -
b1 ,
b0 +
b0 *
b111 )
b0 (
b101 '
0%
0$
0#
b1100 "
0!
$end
#2000
b1 +
0<
0?
0=
0;
b1100 >
#12000
b11111111111111111111111111111111 0
1%
b100000000000000000000000000000000 2
1!
b0 "
b0 1
b1 )
b1 /
b11111111111111111111111111111111 '
b11111111111111111111111111111111 -
b10 ,
1:
16
b0 9
b1 4
b11111111111111111111111111111111 3
b100000101000100010001000010000001110111011100100110000101110000 @
#14000
b10 +
1?
1;
b0 >
#24000
1$
1#
0!
b10000000000000000000000000000000 "
b10000000000000000000000000000000 1
b10000000000000000000000000000000 2
0%
b1111111111111111111111111111111 '
b1111111111111111111111111111111 -
b11 ,
17
0:
18
06
b10000000000000000000000000000000 9
b1111111111111111111111111111111 3
b1000001010001000100010000100000011100110110100101100111011011100110010101100100001000000110111101110110011001010111001001100110011011000110111101110111 @
#26000
b11 +
1<
0?
1=
0;
b10000000000000000000000000000000 >
#36000
0$
b10000000000000000000000000000000 0
1%
b100000000000000000000000000000000 2
1#
1!
b0 "
b0 1
b10000000000000000000000000000000 )
b10000000000000000000000000000000 /
b10000000000000000000000000000000 '
b10000000000000000000000000000000 -
b100 ,
07
1:
16
b0 9
b10000000000000000000000000000000 4
b10000000000000000000000000000000 3
b100000101000100010001000010000001101110011001010110011101100001011101000110100101110110011001010010000000101011001000000110111001100101011001110110000101110100011010010111011001100101001000000110111101110110011001010111001001100110011011000110111101110111 @
#38000
b100 +
0<
1?
1;
b0 >
#48000
0$
b11111111111111111111111111111001 0
0!
b1101 "
b1101 1
b100000000000000000000000000001101 2
0#
1%
b1 (
b1 .
b111 )
b111 /
b10100 '
b10100 -
b101 ,
0:
08
b1101 9
b1 5
b111 4
b10100 3
b10100110101010101000010001000000110001001100001011100110110100101100011 @
#50000
b101 +
0?
0=
b1101 >
#60000
1$
b11111111111111111111111111101100 0
b11111111111111111111111111110011 2
0%
0!
b11111111111111111111111111110011 "
b11111111111111111111111111110011 1
b10100 )
b10100 /
b111 '
b111 -
b110 ,
17
06
b11111111111111111111111111110011 9
b10100 4
b111 3
b1010011010101010100001000100000011011100110010101100111011000010111010001101001011101100110010100100000011100100110010101110011011101010110110001110100 @
#62000
b110 +
1<
0;
b11111111111111111111111111110011 >
#72000
0$
b11111111111111111111111111111111 0
1#
1%
b101111111111111111111111111111111 2
0!
b1111111111111111111111111111111 "
b1111111111111111111111111111111 1
b1 )
b1 /
b10000000000000000000000000000000 '
b10000000000000000000000000000000 -
b111 ,
07
18
16
b1111111111111111111111111111111 9
b1 4
b10000000000000000000000000000000 3
b1010011010101010100001000100000011100110110100101100111011011100110010101100100001000000110111101110110011001010111001001100110011011000110111101110111 @
#74000
b111 +
0<
1=
1;
b1111111111111111111111111111111 >
#84000
b11110000000011111111000000010000 0
b0 2
0#
0%
0!
b111100000000000011110000 "
b111100000000000011110000 1
b10 (
b10 .
b1111111100000000111111110000 )
b1111111100000000111111110000 /
b11110000111100001111000011110000 '
b11110000111100001111000011110000 -
b1000 ,
08
06
b111100000000000011110000 9
b10 5
b1111111100000000111111110000 4
b11110000111100001111000011110000 3
b100000101001110010001000010000001110100011001010111001101110100 @
#86000
b1000 +
0=
0;
b111100000000000011110000 >
#96000
1$
b11110000111100001111000011110001 0
0!
b10101111101011111010111110101111 "
b10101111101011111010111110101111 1
b11 (
b11 .
b1111000011110000111100001111 )
b1111000011110000111100001111 /
b10100101101001011010010110100101 '
b10100101101001011010010110100101 -
b1001 ,
17
b10101111101011111010111110101111 9
b11 5
b1111000011110000111100001111 4
b10100101101001011010010110100101 3
b1001111010100100010000001110100011001010111001101110100 @
#98000
b1001 +
1<
b10101111101011111010111110101111 >
#108000
b10101010101010101010101010101011 0
0!
b11111111111111111111111111111111 "
b11111111111111111111111111111111 1
b100 (
b100 .
b1010101010101010101010101010101 )
b1010101010101010101010101010101 /
b10101010101010101010101010101010 '
b10101010101010101010101010101010 -
b1010 ,
b11111111111111111111111111111111 9
b100 5
b1010101010101010101010101010101 4
b10101010101010101010101010101010 3
b101100001001111010100100010000001110100011001010111001101110100 @
#110000
b1010 +
b11111111111111111111111111111111 >
#120000
0$
b11111111111111111111111111111011 0
0!
b1 "
b1 1
b101 (
b101 .
b101 )
b101 /
b11111111111111111111111111111011 '
b11111111111111111111111111111011 -
b1011 ,
07
b1 9
b101 5
b101 4
b11111111111111111111111111111011 3
b1010011010011000101010000100000001011010011010100100000001111000010000000110101 @
#122000
b1011 +
0<
b1 >
#132000
b101 0
1!
b0 "
b0 1
b11111111111111111111111111111011 )
b11111111111111111111111111111011 /
b101 '
b101 -
b1100 ,
1:
b0 9
b11111111111111111111111111111011 4
b101 3
b1010011010011000101010000100000001101010010000000111100001000000010110100110101 @
#134000
b1100 +
1?
b0 >
#144000
b0 0
0!
b1 "
b1 1
b0 )
b0 /
b10000000000000000000000000000000 '
b10000000000000000000000000000000 -
b1101 ,
0:
b1 9
b0 4
b10000000000000000000000000000000 3
b101001101001100010101000010000001101101011010010110111000100000011011100110010101100111011000010111010001101001011101100110010100100000001111000010000000110000 @
#146000
b1101 +
0?
b1 >
#156000
b1 0
0!
b1 "
b1 1
b110 (
b110 .
b11111111111111111111111111111111 )
b11111111111111111111111111111111 /
b1 '
b1 -
b1110 ,
b110 5
b11111111111111111111111111111111 4
b1 3
b10100110100110001010100010101010010000000110001001000000011110000100000011011010110000101111000 @
#158000
b1110 +
#168000
b11111111111111111111111111111111 0
1!
b0 "
b0 1
b1 )
b1 /
b11111111111111111111111111111111 '
b11111111111111111111111111111111 -
b1111 ,
1:
b0 9
b1 4
b11111111111111111111111111111111 3
b10100110100110001010100010101010010000001101101011000010111100000100000001111000010000000110001 @
#170000
b1111 +
1?
b0 >
#180000
b10000000000000000000000000000001 0
b1111111111111111111111111111111 )
b1111111111111111111111111111111 /
b10000000000000000000000000000000 '
b10000000000000000000000000000000 -
b10000 ,
b1111111111111111111111111111111 4
b10000000000000000000000000000000 3
b10100110100110001010100010101010010000001110101011011100111001101101001011001110110111001100101011001000010000001100011011011110110110101110000011000010111001001100101 @
#182000
b10000 +
#192000
b11111111111111111111111111111011 0
0!
b100000 "
b100000 1
b111 (
b111 .
b101 )
b101 /
b1 '
b1 -
b10001 ,
0:
b100000 9
b111 5
b101 4
b1 3
b101001101001100010011000010000000110001001111000011110000110101 @
#194000
b10001 +
0?
b100000 >
#204000
b11111111111111111111111111111100 0
1!
b0 "
b0 1
b100 )
b100 /
b11110000000000000000000000000000 '
b11110000000000000000000000000000 -
b10010 ,
1:
b0 9
b100 4
b11110000000000000000000000000000 3
b10100110100110001001100001000000110111101110110011001010111001001100110011011000110111101110111001000000111001101101000011010010110011001110100 @
#206000
b10010 +
1?
b0 >
#216000
b11111111111111111111111111100001 0
0!
b1 "
b1 1
b1000 (
b1000 .
b11111 )
b11111 /
b10000000000000000000000000000000 '
b10000000000000000000000000000000 -
b10011 ,
0:
b1 9
b1000 5
b11111 4
b10000000000000000000000000000000 3
b101001101010010010011000010000001101100011011110110011101101001011000110110000101101100001000000111001001101001011001110110100001110100 @
#218000
b10011 +
0?
b1 >
#228000
b11111111111111111111111111111100 0
0!
b1111111111111111111111111111 "
b1111111111111111111111111111 1
b100 )
b100 /
b11111111111111111111111111111111 '
b11111111111111111111111111111111 -
b10100 ,
b1111111111111111111111111111 9
b100 4
b11111111111111111111111111111111 3
b10100110101001001001100001000000111001101101000011010010110011001110100 @
#230000
b10100 +
b1111111111111111111111111111 >
#240000
1$
0!
b11111111111111111111111111111111 "
b11111111111111111111111111111111 1
b1001 (
b1001 .
b10101 ,
17
b11111111111111111111111111111111 9
b1001 5
b101001101010010010000010010000001100001011100100110100101110100011010000110110101100101011101000110100101100011 @
#242000
b10101 +
1<
b11111111111111111111111111111111 >
#252000
b11111111111111111111111111100001 0
0!
b11111111111111111111111111111111 "
b11111111111111111111111111111111 1
b11111 )
b11111 /
b10000000000000000000000000000000 '
b10000000000000000000000000000000 -
b10110 ,
b11111 4
b10000000000000000000000000000000 3
b10100110101001001000001001000000111001101101001011001110110111000100000011001010111100001110100011001010110111001100100 @
#254000
b10110 +
#264000
0$
b1010 0
1%
b100000000000000000000000000000000 2
1!
b0 "
b0 1
b0 (
b0 .
b11111111111111111111111111110110 )
b11111111111111111111111111110110 /
b1010 '
b1010 -
b10111 ,
07
1:
16
b0 9
b0 5
b11111111111111111111111111110110 4
b1010 3
b101101001100101011100100110111100100000011001100110110001100001011001110010000001110100011001010111001101110100 @
#266000
b10111 +
0<
1?
1;
b0 >
