src/alu_control.v
//=====================================================================
// File        : alu_control.v
// Author      : Prabhat Pandey
// Created On  : 15-Feb-2026
// Project     : RV32I Single-Cycle 32-bit RISC-V Processor
// Module Name : alu_control
// Description :
//   This module generates the 4-bit ALUControl signal for the RV32I ALU.
//
//   In the CPU datapath:
//     - The main controller produces a high-level ALUOp (2-bit).
//     - This module uses ALUOp + funct3 + funct7 to decide the exact
//       ALU operation.
//
// Inputs:
//   - alu_op  : 2-bit high-level ALU operation selector
//   - funct3  : instruction funct3 field (instr[14:12])
//   - funct7  : instruction funct7 field (instr[31:25])
//
// Output:
//   - alu_ctrl: 4-bit ALU control to drive alu.v
//
// ALUControl Encoding (must match alu.v):
//   0000 : ADD
//   0001 : SUB
//   0010 : AND
//   0011 : OR
//   0100 : XOR
//   0101 : SLT
//   0110 : SLTU
//   0111 : SLL
//   1000 : SRL
//   1001 : SRA
//
// ALUOp Encoding (defined for this project):
//   00 : Default ADD (loads/stores/address calc)
//   01 : Branch operation (SUB for beq/bne; branch_unit handles compare)
//   10 : R-type (OP)       -> decode using funct3/funct7
//   11 : I-type (OP-IMM)   -> decode using funct3/funct7[5] for shifts
//
// Notes:
//   - For SRLI vs SRAI and SRL vs SRA:
//       funct3 = 101
//       funct7[5] = 0 => SRL/SRLI
//       funct7[5] = 1 => SRA/SRAI
//
// Revision History:
//   - 16-Feb-2026 : Initial version
//=====================================================================

module alu_control (
    input  wire [1:0] alu_op,     // High-level ALUOp from controller
    input  wire [2:0] funct3,     // funct3 field from instruction
    input  wire [6:0] funct7,     // funct7 field from instruction
    output reg  [3:0] alu_ctrl    // Exact ALU control for alu.v
);

    //=================================================================
    // Combinational decode
    //=================================================================
    always @(*) begin

        // Default safe operation
        alu_ctrl = 4'b0000; // ADD

        case (alu_op)

            // ---------------------------------------------------------
            // ALUOp = 00 : Default ADD
            // Used by:
            //   - lw/sw address calculation
            //   - addi (also could be ALUOp=11, but ADD is same)
            //   - jalr base + offset
            //   - auipc (PC + imm)
            // ---------------------------------------------------------
            2'b00: begin
                alu_ctrl = 4'b0000; // ADD
            end

            // ---------------------------------------------------------
            // ALUOp = 01 : Branch operation
            // For BEQ/BNE, subtraction is typically used.
            // For BLT/BGE/BLTU/BGEU, branch_unit will compare directly.
            // ---------------------------------------------------------
            2'b01: begin
                alu_ctrl = 4'b0001; // SUB
            end

            // ---------------------------------------------------------
            // ALUOp = 10 : R-type (OP)
            // Decode using funct3 and funct7.
            // ---------------------------------------------------------
            2'b10: begin
                case (funct3)

                    3'b000: begin
                        // ADD/SUB depends on funct7[5]
                        // funct7 = 0000000 => ADD
                        // funct7 = 0100000 => SUB
                        if (funct7[5] == 1'b1)
                            alu_ctrl = 4'b0001; // SUB
                        else
                            alu_ctrl = 4'b0000; // ADD
                    end

                    3'b111: alu_ctrl = 4'b0010; // AND
                    3'b110: alu_ctrl = 4'b0011; // OR
                    3'b100: alu_ctrl = 4'b0100; // XOR
                    3'b010: alu_ctrl = 4'b0101; // SLT
                    3'b011: alu_ctrl = 4'b0110; // SLTU
                    3'b001: alu_ctrl = 4'b0111; // SLL

                    3'b101: begin
                        // SRL/SRA depends on funct7[5]
                        if (funct7[5] == 1'b1)
                            alu_ctrl = 4'b1001; // SRA
                        else
                            alu_ctrl = 4'b1000; // SRL
                    end

                    default: alu_ctrl = 4'b0000; // ADD safe fallback

                endcase
            end

            // ---------------------------------------------------------
            // ALUOp = 11 : I-type (OP-IMM)
            // Decode using funct3 and funct7 for shifts.
            // ---------------------------------------------------------
            2'b11: begin
                case (funct3)

                    3'b000: alu_ctrl = 4'b0000; // ADDI -> ADD
                    3'b111: alu_ctrl = 4'b0010; // ANDI -> AND
                    3'b110: alu_ctrl = 4'b0011; // ORI  -> OR
                    3'b100: alu_ctrl = 4'b0100; // XORI -> XOR
                    3'b010: alu_ctrl = 4'b0101; // SLTI -> SLT
                    3'b011: alu_ctrl = 4'b0110; // SLTIU -> SLTU
                    3'b001: alu_ctrl = 4'b0111; // SLLI -> SLL

                    3'b101: begin
                        // SRLI/SRAI depends on funct7[5]
                        if (funct7[5] == 1'b1)
                            alu_ctrl = 4'b1001; // SRAI -> SRA
                        else
                            alu_ctrl = 4'b1000; // SRLI -> SRL
                    end

                    default: alu_ctrl = 4'b0000; // ADD safe fallback

                endcase
            end

            default: begin
                alu_ctrl = 4'b0000; // ADD
            end

        endcase
    end

endmodule

RTL_Verification/tb_alu_control.v
//=====================================================================
// File        : tb_alu_control.v
// Author      : Prabhat Pandey
// Created On  : 15-Feb-2026
// Project     : RV32I Single-Cycle 32-bit RISC-V Processor
// Testbench   : tb_alu_control
// Description :
//   Fully self-checking testbench for alu_control.v
//
// ALUOp Encoding (as defined in alu_control.v):
//   00 : Default ADD (loads/stores/address calc)
//   01 : Branch operation (SUB)
//   10 : R-type (OP) decode via funct3/funct7
//   11 : I-type (OP-IMM) decode via funct3/funct7
//
// ALUControl Encoding (must match alu.v):
//   0000 : ADD
//   0001 : SUB
//   0010 : AND
//   0011 : OR
//   0100 : XOR
//   0101 : SLT
//   0110 : SLTU
//   0111 : SLL
//   1000 : SRL
//   1001 : SRA
//
// Verification Features:
//   - Fully self-checking
//   - Input print per test
//   - Expected output print
//   - Actual output print
//   - PASS/FAIL per test
//   - Global counters
//   - Final summary report
//
// Run Commands:
//   iverilog -o ./Verification_Results/result_tb_alu_control ./src/alu_control.v ./RTL_Verification/tb_alu_control.v
//   vvp ./Verification_Results/result_tb_alu_control
//=====================================================================

`timescale 1ns/1ps

module tb_alu_control;

    //=============================================================
    // Testbench Parameters
    //=============================================================
    localparam integer TEST_DELAY = 10; // ns between tests for waveform visibility

    //=============================================================
    // DUT Signals
    //=============================================================
    reg  [1:0] alu_op;
    reg  [2:0] funct3;
    reg  [6:0] funct7;
    wire [3:0] alu_ctrl;

    //=============================================================
    // Instantiate DUT
    //=============================================================
    alu_control dut (
        .alu_op   (alu_op),
        .funct3   (funct3),
        .funct7   (funct7),
        .alu_ctrl (alu_ctrl)
    );

    //=============================================================
    // Global Counters
    //=============================================================
    integer total_tests;
    integer passed_tests;
    integer failed_tests;

    //=============================================================
    // VCD Dump (for GTKWave)
    //=============================================================
    initial begin
        $dumpfile("tb_alu_control.vcd");
        $dumpvars(0, tb_alu_control);
    end

    //=============================================================
    // Task: Divider
    //=============================================================
    task print_divider;
        begin
            $display("----------------------------------------------------------------");
        end
    endtask

    //=============================================================
    // Task: Run One Test
    //=============================================================
    task run_test;
        input [8*70:1] test_name;
        input [1:0]    alu_op_in;
        input [2:0]    funct3_in;
        input [6:0]    funct7_in;
        input [3:0]    expected_ctrl;

        reg [3:0] got_ctrl;
        begin
            total_tests = total_tests + 1;

            print_divider();
            $display("TEST : %s", test_name);

            // Apply inputs
            alu_op = alu_op_in;
            funct3 = funct3_in;
            funct7 = funct7_in;

            #2; // combinational settle
            got_ctrl = alu_ctrl;

            // Print Inputs
            $display("Inputs:");
            $display("   alu_op   = %02b", alu_op_in);
            $display("   funct3   = %03b", funct3_in);
            $display("   funct7   = %07b", funct7_in);
            $display("   funct7[5]= %0d", funct7_in[5]);

            // Print Expected
            $display("");
            $display("Expected:");
            $display("   alu_ctrl = %04b", expected_ctrl);

            // Print Got
            $display("");
            $display("Got:");
            $display("   alu_ctrl = %04b", got_ctrl);

            // Compare
            if (got_ctrl === expected_ctrl) begin
                passed_tests = passed_tests + 1;
                $display("STATUS: PASS");
            end
            else begin
                failed_tests = failed_tests + 1;
                $display("STATUS: FAIL");
            end

            print_divider();
            $display("");

            #(TEST_DELAY);
        end
    endtask

    //=============================================================
    // Main Test Sequence
    //=============================================================
    initial begin

        // Init counters
        total_tests  = 0;
        passed_tests = 0;
        failed_tests = 0;

        // Init inputs
        alu_op = 2'b00;
        funct3 = 3'b000;
        funct7 = 7'b0000000;

        $display("====================================================");
        $display(" ALU_CONTROL VERIFICATION STARTED — Author: Prabhat Pandey");
        $display("====================================================");
        $display("");

        //=========================================================
        // ALUOp = 00 : Always ADD
        //=========================================================
        run_test("ALUOp=00 default ADD (ignore funct fields)",
                 2'b00, 3'b111, 7'b1111111, 4'b0000);

        //=========================================================
        // ALUOp = 01 : Branch -> SUB
        //=========================================================
        run_test("ALUOp=01 branch -> SUB",
                 2'b01, 3'b000, 7'b0000000, 4'b0001);

        //=========================================================
        // ALUOp = 10 : R-type decoding
        //=========================================================

        // ADD
        run_test("R-type ADD (funct3=000, funct7=0000000)",
                 2'b10, 3'b000, 7'b0000000, 4'b0000);

        // SUB
        run_test("R-type SUB (funct3=000, funct7=0100000)",
                 2'b10, 3'b000, 7'b0100000, 4'b0001);

        // AND
        run_test("R-type AND (funct3=111)",
                 2'b10, 3'b111, 7'b0000000, 4'b0010);

        // OR
        run_test("R-type OR (funct3=110)",
                 2'b10, 3'b110, 7'b0000000, 4'b0011);

        // XOR
        run_test("R-type XOR (funct3=100)",
                 2'b10, 3'b100, 7'b0000000, 4'b0100);

        // SLT
        run_test("R-type SLT (funct3=010)",
                 2'b10, 3'b010, 7'b0000000, 4'b0101);

        // SLTU
        run_test("R-type SLTU (funct3=011)",
                 2'b10, 3'b011, 7'b0000000, 4'b0110);

        // SLL
        run_test("R-type SLL (funct3=001)",
                 2'b10, 3'b001, 7'b0000000, 4'b0111);

        // SRL
        run_test("R-type SRL (funct3=101, funct7[5]=0)",
                 2'b10, 3'b101, 7'b0000000, 4'b1000);

        // SRA
        run_test("R-type SRA (funct3=101, funct7[5]=1)",
                 2'b10, 3'b101, 7'b0100000, 4'b1001);

        //=========================================================
        // ALUOp = 11 : I-type OP-IMM decoding
        //=========================================================

        // ADDI
        run_test("I-type ADDI (funct3=000)",
                 2'b11, 3'b000, 7'b0000000, 4'b0000);

        // ANDI
        run_test("I-type ANDI (funct3=111)",
                 2'b11, 3'b111, 7'b0000000, 4'b0010);

        // ORI
        run_test("I-type ORI (funct3=110)",
                 2'b11, 3'b110, 7'b0000000, 4'b0011);

        // XORI
        run_test("I-type XORI (funct3=100)",
                 2'b11, 3'b100, 7'b0000000, 4'b0100);

        // SLTI
        run_test("I-type SLTI (funct3=010)",
                 2'b11, 3'b010, 7'b0000000, 4'b0101);

        // SLTIU
        run_test("I-type SLTIU (funct3=011)",
                 2'b11, 3'b011, 7'b0000000, 4'b0110);

        // SLLI
        run_test("I-type SLLI (funct3=001)",
                 2'b11, 3'b001, 7'b0000000, 4'b0111);

        // SRLI
        run_test("I-type SRLI (funct3=101, funct7[5]=0)",
                 2'b11, 3'b101, 7'b0000000, 4'b1000);

        // SRAI
        run_test("I-type SRAI (funct3=101, funct7[5]=1)",
                 2'b11, 3'b101, 7'b0100000, 4'b1001);

        //=========================================================
        // Default safety test
        //=========================================================
        run_test("Default safety: unknown ALUOp -> ADD",
                 2'bxx, 3'bxxx, 7'bxxxxxxx, 4'b0000);

        //=========================================================
        // Final Summary Report
        //=========================================================
        $display("====================================================");
        $display(" ALU_CONTROL VERIFICATION REPORT");
        $display("====================================================");
        $display("   Total Tests   : %0d", total_tests);
        $display("   Passed        : %0d", passed_tests);
        $display("   Failed        : %0d", failed_tests);
        $display("====================================================");

        if (failed_tests == 0) begin
            $display("STATUS: ALL TESTS PASSED");
        end
        else begin
            $display("STATUS: SOME TESTS FAILED");
        end

        $display("====================================================");
        $display("");

        $finish;
    end

endmodule

Verification_Results/tb_alu_control.vcd
$date
	Wed Feb 25 22:41:49 2026
$end
$version
	Icarus Verilog
$end
$timescale
	1ps
$end
$scope module tb_alu_control $end
$var wire 4 ! alu_ctrl [3:0] $end
$var parameter 32 " TEST_DELAY $end
$var reg 2 # alu_op [1:0] $end
$var reg 3 $ funct3 [2:0] $end
$var reg 7 % funct7 [6:0] $end
$var integer 32 & failed_tests [31:0] $end
$var integer 32 ' passed_tests [31:0] $end
$var integer 32 ( total_tests [31:0] $end
$scope module dut $end
$var wire 2 ) alu_op [1:0] $end
$var wire 3 * funct3 [2:0] $end
$var wire 7 + funct7 [6:0] $end
$var reg 4 , alu_ctrl [3:0] $end
$upscope $end
$scope task print_divider $end
$upscope $end
$scope task run_test $end
$var reg 2 - alu_op_in [1:0] $end
$var reg 4 . expected_ctrl [3:0] $end
$var reg 3 / funct3_in [2:0] $end
$var reg 7 0 funct7_in [6:0] $end
$var reg 4 1 got_ctrl [3:0] $end
$var reg 560 2 test_name [560:1] $end
$upscope $end
$upscope $end
$enddefinitions $end
$comment Show the parameter values. $end
$dumpall
b1010 "
$end
#0
$dumpvars
b10000010100110001010101010011110111000000111101001100000011000000100000011001000110010101100110011000010111010101101100011101000010000001000001010001000100010000100000001010000110100101100111011011100110111101110010011001010010000001100110011101010110111001100011011101000010000001100110011010010110010101101100011001000111001100101001 2
bx 1
b1111111 0
b111 /
b0 .
b0 -
b0 ,
b1111111 +
b111 *
b0 )
b1 (
b0 '
b0 &
b1111111 %
b111 $
b0 #
b0 !
$end
#2000
b1 '
b0 1
#12000
b1 !
b1 ,
b0 %
b0 +
b0 $
b0 *
b1 #
b1 )
b10 (
b1 .
b0 0
b0 /
b1 -
b1000001010011000101010101001111011100000011110100110000001100010010000001100010011100100110000101101110011000110110100000100000001011010011111000100000010100110101010101000010 2
#14000
b10 '
b1 1
#24000
b0 !
b0 ,
b10 #
b10 )
b11 (
b0 .
b10 -
b10100100010110101110100011110010111000001100101001000000100000101000100010001000010000000101000011001100111010101101110011000110111010000110011001111010011000000110000001100000010110000100000011001100111010101101110011000110111010000110111001111010011000000110000001100000011000000110000001100000011000000101001 2
#26000
b11 '
b0 1
#36000
b1 !
b1 ,
b100000 %
b100000 +
b100 (
b1 .
b100000 0
b10100100010110101110100011110010111000001100101001000000101001101010101010000100010000000101000011001100111010101101110011000110111010000110011001111010011000000110000001100000010110000100000011001100111010101101110011000110111010000110111001111010011000000110001001100000011000000110000001100000011000000101001 2
#38000
b100 '
b1 1
#48000
b10 !
b10 ,
b0 %
b0 +
b111 $
b111 *
b101 (
b10 .
b0 0
b111 /
b101001000101101011101000111100101110000011001010010000001000001010011100100010000100000001010000110011001110101011011100110001101110100001100110011110100110001001100010011000100101001 2
#50000
b101 '
b10 1
#60000
b11 !
b11 ,
b110 $
b110 *
b110 (
b11 .
b110 /
b1010010001011010111010001111001011100000110010100100000010011110101001000100000001010000110011001110101011011100110001101110100001100110011110100110001001100010011000000101001 2
#62000
b110 '
b11 1
#72000
b100 !
b100 ,
b100 $
b100 *
b111 (
b100 .
b100 /
b101001000101101011101000111100101110000011001010010000001011000010011110101001000100000001010000110011001110101011011100110001101110100001100110011110100110001001100000011000000101001 2
#74000
b111 '
b100 1
#84000
b101 !
b101 ,
b10 $
b10 *
b1000 (
b101 .
b10 /
b101001000101101011101000111100101110000011001010010000001010011010011000101010000100000001010000110011001110101011011100110001101110100001100110011110100110000001100010011000000101001 2
#86000
b1000 '
b101 1
#96000
b110 !
b110 ,
b11 $
b11 *
b1001 (
b110 .
b11 /
b10100100010110101110100011110010111000001100101001000000101001101001100010101000101010100100000001010000110011001110101011011100110001101110100001100110011110100110000001100010011000100101001 2
#98000
b1001 '
b110 1
#108000
b111 !
b111 ,
b1 $
b1 *
b1010 (
b111 .
b1 /
b101001000101101011101000111100101110000011001010010000001010011010011000100110000100000001010000110011001110101011011100110001101110100001100110011110100110000001100000011000100101001 2
#110000
b1010 '
b111 1
#120000
b1000 !
b1000 ,
b101 $
b101 *
b1011 (
b1000 .
b101 /
b10100100010110101110100011110010111000001100101001000000101001101010010010011000010000000101000011001100111010101101110011000110111010000110011001111010011000100110000001100010010110000100000011001100111010101101110011000110111010000110111010110110011010101011101001111010011000000101001 2
#122000
b1011 '
b1000 1
#132000
b1001 !
b1001 ,
b100000 %
b100000 +
b1100 (
b1001 .
b100000 0
b10100100010110101110100011110010111000001100101001000000101001101010010010000010010000000101000011001100111010101101110011000110111010000110011001111010011000100110000001100010010110000100000011001100111010101101110011000110111010000110111010110110011010101011101001111010011000100101001 2
#134000
b1100 '
b1001 1
#144000
b0 !
b0 ,
b0 %
b0 +
b0 $
b0 *
b11 #
b11 )
b1101 (
b0 .
b0 0
b0 /
b11 -
b10010010010110101110100011110010111000001100101001000000100000101000100010001000100100100100000001010000110011001110101011011100110001101110100001100110011110100110000001100000011000000101001 2
#146000
b1101 '
b0 1
#156000
b10 !
b10 ,
b111 $
b111 *
b1110 (
b10 .
b111 /
b10010010010110101110100011110010111000001100101001000000100000101001110010001000100100100100000001010000110011001110101011011100110001101110100001100110011110100110001001100010011000100101001 2
#158000
b1110 '
b10 1
#168000
b11 !
b11 ,
b110 $
b110 *
b1111 (
b11 .
b110 /
b100100100101101011101000111100101110000011001010010000001001111010100100100100100100000001010000110011001110101011011100110001101110100001100110011110100110001001100010011000000101001 2
#170000
b1111 '
b11 1
#180000
b100 !
b100 ,
b100 $
b100 *
b10000 (
b100 .
b100 /
b10010010010110101110100011110010111000001100101001000000101100001001111010100100100100100100000001010000110011001110101011011100110001101110100001100110011110100110001001100000011000000101001 2
#182000
b10000 '
b100 1
#192000
b101 !
b101 ,
b10 $
b10 *
b10001 (
b101 .
b10 /
b10010010010110101110100011110010111000001100101001000000101001101001100010101000100100100100000001010000110011001110101011011100110001101110100001100110011110100110000001100010011000000101001 2
#194000
b10001 '
b101 1
#204000
b110 !
b110 ,
b11 $
b11 *
b10010 (
b110 .
b11 /
b1001001001011010111010001111001011100000110010100100000010100110100110001010100010010010101010100100000001010000110011001110101011011100110001101110100001100110011110100110000001100010011000100101001 2
#206000
b10010 '
b110 1
#216000
b111 !
b111 ,
b1 $
b1 *
b10011 (
b111 .
b1 /
b10010010010110101110100011110010111000001100101001000000101001101001100010011000100100100100000001010000110011001110101011011100110001101110100001100110011110100110000001100000011000100101001 2
#218000
b10011 '
b111 1
#228000
b1000 !
b1000 ,
b101 $
b101 *
b10100 (
b1000 .
b101 /
b1001001001011010111010001111001011100000110010100100000010100110101001001001100010010010010000000101000011001100111010101101110011000110111010000110011001111010011000100110000001100010010110000100000011001100111010101101110011000110111010000110111010110110011010101011101001111010011000000101001 2
#230000
b10100 '
b1000 1
#240000
b1001 !
b1001 ,
b100000 %
b100000 +
b10101 (
b1001 .
b100000 0
b1001001001011010111010001111001011100000110010100100000010100110101001001000001010010010010000000101000011001100111010101101110011000110111010000110011001111010011000100110000001100010010110000100000011001100111010101101110011000110111010000110111010110110011010101011101001111010011000100101001 2
#242000
b10101 '
b1001 1
#252000
b0 !
b0 ,
bx %
bx +
bx $
bx *
bx #
bx )
b10110 (
b0 .
bx 0
bx /
bx -
b10001000110010101100110011000010111010101101100011101000010000001110011011000010110011001100101011101000111100100111010001000000111010101101110011010110110111001101111011101110110111000100000010000010100110001010101010011110111000000100000001011010011111000100000010000010100010001000100 2
#254000
b10110 '
b0 1
