src/imem.v
//=====================================================================
// File        : imem.v
// Author      : Prabhat Pandey
// Created On  : 13-Feb-2026
// Project     : RV32I Single-Cycle 32-bit RISC-V Processor
// Module Name : imem
// Description :
//   This module implements Instruction Memory (IMEM) for an RV32
//   single-cycle RISC-V processor.
//
//   The instruction memory is modeled as a ROM-like array initialized
//   using $readmemh from a HEX file.
//
//   Key Points:
//   - Instructions are 32-bit wide (one word)
//   - RISC-V instructions are always 4-byte aligned
//   - Therefore, the memory is indexed using addr[31:2] (word address)
//
// Behavior:
//   - Combinational read: instr updates immediately with addr changes
//   - No write port (ROM behavior for instruction memory)
//
// Notes:
//   - This is perfect for simulation and FPGA-style ROM.
//   - For ASIC, IMEM would be replaced by a real ROM or instruction cache.
//
// File Format for $readmemh:
//   Each line should contain ONE 32-bit instruction in HEX.
//   Example (program.hex):
//      00000013   // NOP  (addi x0, x0, 0)
//      00100093   // addi x1, x0, 1
//
// Revision History:
//   - 13-Feb-2026 : Initial version
//=====================================================================

module imem #(
    parameter MEM_DEPTH_WORDS = 1024,                  // Total words in IMEM
    parameter MEM_INIT_FILE   = "program.hex"          // HEX file for initialization
)(
    input  wire [31:0] addr,                           // Byte address from PC
    output wire [31:0] instr                           // 32-bit instruction output
);

    //=================================================================
    // Instruction Memory Storage
    //=================================================================
    // Each entry is one 32-bit RISC-V instruction word.
    // MEM_DEPTH_WORDS = number of 32-bit words.
    //=================================================================
    reg [31:0] mem [0:MEM_DEPTH_WORDS-1];

    //=================================================================
    // Memory Initialization
    //=================================================================
    // Loads instruction words from a hex file at simulation start.
    // If file is missing, IMEM will contain X/unknown values.
    //=================================================================
    initial begin
        $readmemh(MEM_INIT_FILE, mem);
    end

    //=================================================================
    // Address Mapping (Word Addressing)
    //=================================================================
    // RISC-V instructions are 4-byte aligned.
    // So:
    //   PC = byte address
    //   Index = PC / 4 = PC[31:2]
    //=================================================================
    wire [$clog2(MEM_DEPTH_WORDS)-1:0] word_index;
    assign word_index = addr[31:2];

    //=================================================================
    // Combinational Read Output
    //=================================================================
    // Reads instruction directly from memory.
    // No clock required (ROM-like).
    //=================================================================
    assign instr = mem[word_index];

endmodule

RTL_Verification/tb_imem_program_2.v
//=====================================================================
// File        : tb_imem_program_2.v
// Author      : Prabhat Pandey
// Created On  : 25-Feb-2026
// Project     : RV32I Single-Cycle 32-bit RISC-V Processor
// Testbench   : tb_imem_program_2
// Description :
//   Fully self-checking testbench for imem.v using program_2.hex
//
//   This testbench verifies:
//     1) Instruction memory reads correct 32-bit words
//     2) Addressing is word-based (addr[31:2])
//     3) Multiple sequential fetches return expected values
//
// Verification Features:
//   - Fully self-checking
//   - Input print for each test
//   - Expected output print
//   - Actual output print
//   - PASS/FAIL per test case
//   - Global counters for total/pass/fail
//   - Final verification summary report
//
// Run Commands:
//   iverilog -o ./Verification_Results/result_tb_imem_program_2 \
//       ./src/imem.v ./RTL_Verification/tb_imem_program_2.v
//
//   vvp ./Verification_Results/result_tb_imem_program_2
//
// IMPORTANT:
//   This testbench loads program_2.hex into DUT memory (simulation-only).
//   Ensure program_2.hex is present in the simulation working directory.
//=====================================================================

`timescale 1ns/1ps

module tb_imem_program_2;

    //=============================================================
    // Testbench Parameters
    //=============================================================
    localparam integer TEST_DELAY = 10; // ns between tests for waveform visibility

    //=============================================================
    // DUT Signals
    //=============================================================
    reg  [31:0] addr;
    wire [31:0] instr;

    //=============================================================
    // Instantiate DUT
    //=============================================================
    imem #(
        .MEM_DEPTH_WORDS(4096)
    ) dut (
        .addr  (addr),
        .instr (instr)
    );

    //=============================================================
    // Global Verification Counters
    //=============================================================
    integer total_tests;
    integer passed_tests;
    integer failed_tests;

    //=============================================================
    // VCD Dump (for GTKWave)
    //=============================================================
    initial begin
        $dumpfile("tb_imem_program_2.vcd");
        $dumpvars(0, tb_imem_program_2);
    end

    //=============================================================
    // Task: Divider
    //=============================================================
    task print_divider;
        begin
            $display("----------------------------------------------------------------");
        end
    endtask

    //=============================================================
    // Task: Run a Single IMEM Read Test
    //=============================================================
    // Inputs:
    //   test_name      : string name of the test
    //   addr_in        : byte address applied to IMEM
    //   expected_instr : expected 32-bit instruction output
    //
    // Behavior:
    //   - Applies addr
    //   - Waits small time for combinational propagation
    //   - Checks instr
    //   - Prints PASS/FAIL
    //=============================================================
    task run_test;
        input [8*60:1] test_name;
        input [31:0]   addr_in;
        input [31:0]   expected_instr;

        reg [31:0] got_instr;
        begin
            total_tests = total_tests + 1;

            print_divider();
            $display("TEST : %s", test_name);

            // Apply input address
            addr = addr_in;

            // Wait for combinational output to settle
            #2;
            got_instr = instr;

            // Print Inputs
            $display("Inputs:");
            $display("   addr (byte) = %08h", addr_in);
            $display("   addr[31:2]  = %08h", addr_in >> 2);

            // Print Expected
            $display("");
            $display("Expected:");
            $display("   instr       = %08h", expected_instr);

            // Print Got
            $display("");
            $display("Got:");
            $display("   instr       = %08h", got_instr);

            // Compare
            if (got_instr === expected_instr) begin
                passed_tests = passed_tests + 1;
                $display("STATUS: PASS");
            end
            else begin
                failed_tests = failed_tests + 1;
                $display("STATUS: FAIL");
            end

            print_divider();
            $display("");

            #(TEST_DELAY);
        end
    endtask

    //=============================================================
    // Main Test Sequence
    //=============================================================
    integer idx;
    reg [31:0] expected_instr [0:20];
    reg [31:0] expected_addr  [0:20];
    reg [8*80:1] step_name    [0:20];

    initial begin

        // Init counters
        total_tests  = 0;
        passed_tests = 0;
        failed_tests = 0;

        // Init inputs
        addr = 32'h0000_0000;

        // Load program into IMEM (simulation-only)
        $readmemh("program_2.hex", dut.mem);

        $display("====================================================");
        $display(" IMEM VERIFICATION STARTED — Author: Prabhat Pandey");
        $display("====================================================");
        $display("");

        // ----------------------------------------------------------
        // program_2.hex reference:
        // Index 0  : 00000013
        // Index 1  : 00a00093
        // Index 2  : 01400113
        // Index 3  : 002081b3
        // Index 4  : 40208233
        // Index 5  : 0ff3f293
        // Index 6  : 0f016313
        // Index 7  : 0552c393
        // Index 8  : 00209413
        // Index 9  : 0011d493
        // Index 10 : 00f0a513
        // Index 11 : 019135b3
        // Index 12 : 00302023
        // Index 13 : 00002603
        // Index 14 : 00c18463
        // Index 15 : 06300693
        // Index 16 : 008007ef
        // Index 17 : 12345737
        // Index 18 : 00000817
        // Index 19 : 00100893
        // Index 20 : fe0006e3
        // ----------------------------------------------------------

        // Expected full program fetch list
        expected_addr[0]  = 32'h0000_0000;
        expected_instr[0] = 32'h0000_0013;
        step_name[0]      = "Fetch: NOP (ADDI x0, x0, 0) @ PC=0x00000000";

        expected_addr[1]  = 32'h0000_0004;
        expected_instr[1] = 32'h00a0_0093;
        step_name[1]      = "Fetch: ADDI x1, x0, 10 @ PC=0x00000004";

        expected_addr[2]  = 32'h0000_0008;
        expected_instr[2] = 32'h0140_0113;
        step_name[2]      = "Fetch: ADDI x2, x0, 20 @ PC=0x00000008";

        expected_addr[3]  = 32'h0000_000C;
        expected_instr[3] = 32'h0020_81b3;
        step_name[3]      = "Fetch: ADD x3, x1, x2 @ PC=0x0000000C";

        expected_addr[4]  = 32'h0000_0010;
        expected_instr[4] = 32'h4020_8233;
        step_name[4]      = "Fetch: SUB x4, x1, x2 @ PC=0x00000010";

        expected_addr[5]  = 32'h0000_0014;
        expected_instr[5] = 32'h0ff3_f293;
        step_name[5]      = "Fetch: ANDI x5, x7, 255 @ PC=0x00000014";

        expected_addr[6]  = 32'h0000_0018;
        expected_instr[6] = 32'h0f01_6313;
        step_name[6]      = "Fetch: ORI x6, x2, 240 @ PC=0x00000018";

        expected_addr[7]  = 32'h0000_001C;
        expected_instr[7] = 32'h0552_c393;
        step_name[7]      = "Fetch: XORI x7, x5, 85 @ PC=0x0000001C";

        expected_addr[8]  = 32'h0000_0020;
        expected_instr[8] = 32'h0020_9413;
        step_name[8]      = "Fetch: SLLI x8, x1, 2 @ PC=0x00000020";

        expected_addr[9]  = 32'h0000_0024;
        expected_instr[9] = 32'h0011_d493;
        step_name[9]      = "Fetch: SRLI x9, x3, 1 @ PC=0x00000024";

        expected_addr[10]  = 32'h0000_0028;
        expected_instr[10] = 32'h00f0_a513;
        step_name[10]      = "Fetch: SLTI x10, x1, 15 @ PC=0x00000028";

        expected_addr[11]  = 32'h0000_002C;
        expected_instr[11] = 32'h0191_35b3;
        step_name[11]      = "Fetch: SLTU x11, x2, x25 @ PC=0x0000002C";

        expected_addr[12]  = 32'h0000_0030;
        expected_instr[12] = 32'h0030_2023;
        step_name[12]      = "Fetch: SW x3, 0(x0) @ PC=0x00000030";

        expected_addr[13]  = 32'h0000_0034;
        expected_instr[13] = 32'h0000_2603;
        step_name[13]      = "Fetch: LW x12, 0(x0) @ PC=0x00000034";

        expected_addr[14]  = 32'h0000_0038;
        expected_instr[14] = 32'h00c1_8463;
        step_name[14]      = "Fetch: BEQ x3, x12, +8 @ PC=0x00000038";

        expected_addr[15]  = 32'h0000_003C;
        expected_instr[15] = 32'h0630_0693;
        step_name[15]      = "Fetch: ADDI x13, x0, 99 @ PC=0x0000003C";

        expected_addr[16]  = 32'h0000_0040;
        expected_instr[16] = 32'h0080_07ef;
        step_name[16]      = "Fetch: JAL x15, +8 @ PC=0x00000040";

        expected_addr[17]  = 32'h0000_0044;
        expected_instr[17] = 32'h1234_5737;
        step_name[17]      = "Fetch: LUI x14, 0x12345 @ PC=0x00000044";

        expected_addr[18]  = 32'h0000_0048;
        expected_instr[18] = 32'h0000_0817;
        step_name[18]      = "Fetch: AUIPC x16, 0x0 @ PC=0x00000048";

        expected_addr[19]  = 32'h0000_004C;
        expected_instr[19] = 32'h0010_0893;
        step_name[19]      = "Fetch: ADDI x17, x0, 1 @ PC=0x0000004C";

        expected_addr[20]  = 32'h0000_0050;
        expected_instr[20] = 32'hfe00_06e3;
        step_name[20]      = "Fetch: BEQ x0, x0, -20 @ PC=0x00000050";

        // Full program fetch verification
        for (idx = 0; idx <= 20; idx = idx + 1) begin
            run_test(step_name[idx], expected_addr[idx], expected_instr[idx]);
        end

        // Test: word addressing behavior
        // PC=0x00000005 should still index word 1 because addr[31:2] = 1
        // (In real CPU PC won't be unaligned, but we verify indexing logic)
        run_test("Unaligned addr -> word 1 (ADDI x1, x0, 10)", 32'h0000_0005, 32'h00a0_0093);

        //=========================================================
        // Final Summary Report
        //=========================================================
        $display("====================================================");
        $display(" IMEM VERIFICATION REPORT");
        $display("====================================================");
        $display("   Total Tests   : %0d", total_tests);
        $display("   Passed        : %0d", passed_tests);
        $display("   Failed        : %0d", failed_tests);
        $display("====================================================");

        if (failed_tests == 0) begin
            $display("STATUS: ALL TESTS PASSED");
        end
        else begin
            $display("STATUS: SOME TESTS FAILED");
        end

        $display("====================================================");
        $display("");

        $finish;
    end

endmodule

Verification_Results/tb_imem_program_2.vcd
$date
	Wed Feb 25 22:41:50 2026
$end
$version
	Icarus Verilog
$end
$timescale
	1ps
$end
$scope module tb_imem_program_2 $end
$var wire 32 ! instr [31:0] $end
$var parameter 32 " TEST_DELAY $end
$var reg 32 # addr [31:0] $end
$var integer 32 $ failed_tests [31:0] $end
$var integer 32 % idx [31:0] $end
$var integer 32 & passed_tests [31:0] $end
$var integer 32 ' total_tests [31:0] $end
$scope module dut $end
$var wire 32 ( addr [31:0] $end
$var wire 32 ) instr [31:0] $end
$var wire 12 * word_index [11:0] $end
$var parameter 32 + MEM_DEPTH_WORDS $end
$upscope $end
$scope task print_divider $end
$upscope $end
$scope task run_test $end
$var reg 32 , addr_in [31:0] $end
$var reg 32 - expected_instr [31:0] $end
$var reg 32 . got_instr [31:0] $end
$var reg 480 / test_name [480:1] $end
$upscope $end
$upscope $end
$enddefinitions $end
$comment Show the parameter values. $end
$dumpall
b1000000000000 +
b1010 "
$end
#0
$dumpvars
b1000110011001010111010001100011011010000011101000100000010011100100111101010000001000000010100001000001010001000100010001001001001000000111100000110000001011000010000001111000001100000010110000100000001100000010100100100000010000000010000001010000010000110011110100110000011110000011000000110000001100000011000000110000001100000011000000110000 /
bx .
b10011 -
b0 ,
b0 *
b10011 )
b0 (
b1 '
b0 &
b0 %
b0 $
b0 #
b10011 !
$end
#2000
b1 &
b10011 .
#12000
b101000000000000010010011 !
b101000000000000010010011 )
b1 *
b100 #
b100 (
b10 '
b101000000000000010010011 -
b100 ,
b100011001100101011101000110001101101000001110100010000001000001010001000100010001001001001000000111100000110001001011000010000001111000001100000010110000100000001100010011000000100000010000000010000001010000010000110011110100110000011110000011000000110000001100000011000000110000001100000011000000110100 /
b1 %
#14000
b10 &
b101000000000000010010011 .
#24000
b1010000000000000100010011 !
b1010000000000000100010011 )
b10 *
b1000 #
b1000 (
b11 '
b1010000000000000100010011 -
b1000 ,
b100011001100101011101000110001101101000001110100010000001000001010001000100010001001001001000000111100000110010001011000010000001111000001100000010110000100000001100100011000000100000010000000010000001010000010000110011110100110000011110000011000000110000001100000011000000110000001100000011000000111000 /
b10 %
#26000
b11 &
b1010000000000000100010011 .
#36000
b1000001000000110110011 !
b1000001000000110110011 )
b11 *
b1100 #
b1100 (
b100 '
b1000001000000110110011 -
b1100 ,
b1000110011001010111010001100011011010000011101000100000010000010100010001000100001000000111100000110011001011000010000001111000001100010010110000100000011110000011001000100000010000000010000001010000010000110011110100110000011110000011000000110000001100000011000000110000001100000011000001000011 /
b11 %
#38000
b100 &
b1000001000000110110011 .
#48000
b1000000001000001000001000110011 !
b1000000001000001000001000110011 )
b100 *
b10000 #
b10000 (
b101 '
b1000000001000001000001000110011 -
b10000 ,
b1000110011001010111010001100011011010000011101000100000010100110101010101000010001000000111100000110100001011000010000001111000001100010010110000100000011110000011001000100000010000000010000001010000010000110011110100110000011110000011000000110000001100000011000000110000001100000011000100110000 /
b100 %
#50000
b101 &
b1000000001000001000001000110011 .
#60000
b1111111100111111001010010011 !
b1111111100111111001010010011 )
b101 *
b10100 #
b10100 (
b110 '
b1111111100111111001010010011 -
b10100 ,
b10001100110010101110100011000110110100000111010001000000100000101001110010001000100100100100000011110000011010100101100001000000111100000110111001011000010000000110010001101010011010100100000010000000010000001010000010000110011110100110000011110000011000000110000001100000011000000110000001100000011000100110100 /
b101 %
#62000
b110 &
b1111111100111111001010010011 .
#72000
b1111000000010110001100010011 !
b1111000000010110001100010011 )
b110 *
b11000 #
b11000 (
b111 '
b1111000000010110001100010011 -
b11000 ,
b100011001100101011101000110001101101000001110100010000001001111010100100100100100100000011110000011011000101100001000000111100000110010001011000010000000110010001101000011000000100000010000000010000001010000010000110011110100110000011110000011000000110000001100000011000000110000001100000011000100111000 /
b110 %
#74000
b111 &
b1111000000010110001100010011 .
#84000
b101010100101100001110010011 !
b101010100101100001110010011 )
b111 *
b11100 #
b11100 (
b1000 '
b101010100101100001110010011 -
b11100 ,
b100011001100101011101000110001101101000001110100010000001011000010011110101001001001001001000000111100000110111001011000010000001111000001101010010110000100000001110000011010100100000010000000010000001010000010000110011110100110000011110000011000000110000001100000011000000110000001100000011000101000011 /
b111 %
#86000
b1000 &
b101010100101100001110010011 .
#96000
b1000001001010000010011 !
b1000001001010000010011 )
b1000 *
b100000 #
b100000 (
b1001 '
b1000001001010000010011 -
b100000 ,
b1000110011001010111010001100011011010000011101000100000010100110100110001001100010010010010000001111000001110000010110000100000011110000011000100101100001000000011001000100000010000000010000001010000010000110011110100110000011110000011000000110000001100000011000000110000001100000011001000110000 /
b1000 %
#98000
b1001 &
b1000001001010000010011 .
#108000
b100011101010010010011 !
b100011101010010010011 )
b1001 *
b100100 #
b100100 (
b1010 '
b100011101010010010011 -
b100100 ,
b1000110011001010111010001100011011010000011101000100000010100110101001001001100010010010010000001111000001110010010110000100000011110000011001100101100001000000011000100100000010000000010000001010000010000110011110100110000011110000011000000110000001100000011000000110000001100000011001000110100 /
b1001 %
#110000
b1010 &
b100011101010010010011 .
#120000
b111100001010010100010011 !
b111100001010010100010011 )
b1010 *
b101000 #
b101000 (
b1011 '
b111100001010010100010011 -
b101000 ,
b10001100110010101110100011000110110100000111010001000000101001101001100010101000100100100100000011110000011000100110000001011000010000001111000001100010010110000100000001100010011010100100000010000000010000001010000010000110011110100110000011110000011000000110000001100000011000000110000001100000011001000111000 /
b1010 %
#122000
b1011 &
b111100001010010100010011 .
#132000
b1100100010011010110110011 !
b1100100010011010110110011 )
b1011 *
b101100 #
b101100 (
b1100 '
b1100100010011010110110011 -
b101100 ,
b1000110011001010111010001100011011010000011101000100000010100110100110001010100010101010010000001111000001100010011000100101100001000000111100000110010001011000010000001111000001100100011010100100000010000000010000001010000010000110011110100110000011110000011000000110000001100000011000000110000001100000011001001000011 /
b1011 %
#134000
b1100 &
b1100100010011010110110011 .
#144000
b1100000010000000100011 !
b1100000010000000100011 )
b1100 *
b110000 #
b110000 (
b1101 '
b1100000010000000100011 -
b110000 ,
b100011001100101011101000110001101101000001110100010000001010011010101110010000001111000001100110010110000100000001100000010100001111000001100000010100100100000010000000010000001010000010000110011110100110000011110000011000000110000001100000011000000110000001100000011001100110000 /
b1100 %
#146000
b1101 &
b1100000010000000100011 .
#156000
b10011000000011 !
b10011000000011 )
b1101 *
b110100 #
b110100 (
b1110 '
b10011000000011 -
b110100 ,
b10001100110010101110100011000110110100000111010001000000100110001010111001000000111100000110001001100100010110000100000001100000010100001111000001100000010100100100000010000000010000001010000010000110011110100110000011110000011000000110000001100000011000000110000001100000011001100110100 /
b1101 %
#158000
b1110 &
b10011000000011 .
#168000
b110000011000010001100011 !
b110000011000010001100011 )
b1110 *
b111000 #
b111000 (
b1111 '
b110000011000010001100011 -
b111000 ,
b100011001100101011101000110001101101000001110100010000001000010010001010101000100100000011110000011001100101100001000000111100000110001001100100010110000100000001010110011100000100000010000000010000001010000010000110011110100110000011110000011000000110000001100000011000000110000001100000011001100111000 /
b1110 %
#170000
b1111 &
b110000011000010001100011 .
#180000
b110001100000000011010010011 !
b110001100000000011010010011 )
b1111 *
b111100 #
b111100 (
b10000 '
b110001100000000011010010011 -
b111100 ,
b10001100110010101110100011000110110100000111010001000000100000101000100010001000100100100100000011110000011000100110011001011000010000001111000001100000010110000100000001110010011100100100000010000000010000001010000010000110011110100110000011110000011000000110000001100000011000000110000001100000011001101000011 /
b1111 %
#182000
b10000 &
b110001100000000011010010011 .
#192000
b100000000000011111101111 !
b100000000000011111101111 )
b10000 *
b1000000 #
b1000000 (
b10001 '
b100000000000011111101111 -
b1000000 ,
b1000110011001010111010001100011011010000011101000100000010010100100000101001100001000000111100000110001001101010010110000100000001010110011100000100000010000000010000001010000010000110011110100110000011110000011000000110000001100000011000000110000001100000011010000110000 /
b10000 %
#194000
b10001 &
b100000000000011111101111 .
#204000
b10010001101000101011100110111 !
b10010001101000101011100110111 )
b10001 *
b1000100 #
b1000100 (
b10010 '
b10010001101000101011100110111 -
b1000100 ,
b10001100110010101110100011000110110100000111010001000000100110001010101010010010010000001111000001100010011010000101100001000000011000001111000001100010011001000110011001101000011010100100000010000000010000001010000010000110011110100110000011110000011000000110000001100000011000000110000001100000011010000110100 /
b10001 %
#206000
b10010 &
b10010001101000101011100110111 .
#216000
b100000010111 !
b100000010111 )
b10010 *
b1001000 #
b1001000 (
b10011 '
b100000010111 -
b1001000 ,
b1000110011001010111010001100011011010000011101000100000010000010101010101001001010100000100001100100000011110000011000100110110001011000010000000110000011110000011000000100000010000000010000001010000010000110011110100110000011110000011000000110000001100000011000000110000001100000011010000111000 /
b10010 %
#218000
b10011 &
b100000010111 .
#228000
b100000000100010010011 !
b100000000100010010011 )
b10011 *
b1001100 #
b1001100 (
b10100 '
b100000000100010010011 -
b1001100 ,
b100011001100101011101000110001101101000001110100010000001000001010001000100010001001001001000000111100000110001001101110010110000100000011110000011000000101100001000000011000100100000010000000010000001010000010000110011110100110000011110000011000000110000001100000011000000110000001100000011010001000011 /
b10011 %
#230000
b10100 &
b100000000100010010011 .
#240000
b11111110000000000000011011100011 !
b11111110000000000000011011100011 )
b10100 *
b1010000 #
b1010000 (
b10101 '
b11111110000000000000011011100011 -
b1010000 ,
b100011001100101011101000110001101101000001110100010000001000010010001010101000100100000011110000011000000101100001000000111100000110000001011000010000000101101001100100011000000100000010000000010000001010000010000110011110100110000011110000011000000110000001100000011000000110000001100000011010100110000 /
b10100 %
#242000
b10101 &
b11111110000000000000011011100011 .
#252000
b101000000000000010010011 !
b101000000000000010010011 )
b1 *
b101 #
b101 (
b10110 '
b101000000000000010010011 -
b101 ,
b10101010110111001100001011011000110100101100111011011100110010101100100001000000110000101100100011001000111001000100000001011010011111000100000011101110110111101110010011001000010000000110001001000000010100001000001010001000100010001001001001000000111100000110001001011000010000001111000001100000010110000100000001100010011000000101001 /
b10101 %
#254000
b10110 &
b101000000000000010010011 .
