src/imem.v
//=====================================================================
// File        : imem.v
// Author      : Prabhat Pandey
// Created On  : 13-Feb-2026
// Project     : RV32I Single-Cycle 32-bit RISC-V Processor
// Module Name : imem
// Description :
//   This module implements Instruction Memory (IMEM) for an RV32
//   single-cycle RISC-V processor.
//
//   The instruction memory is modeled as a ROM-like array initialized
//   using $readmemh from a HEX file.
//
//   Key Points:
//   - Instructions are 32-bit wide (one word)
//   - RISC-V instructions are always 4-byte aligned
//   - Therefore, the memory is indexed using addr[31:2] (word address)
//
// Behavior:
//   - Combinational read: instr updates immediately with addr changes
//   - No write port (ROM behavior for instruction memory)
//
// Notes:
//   - This is perfect for simulation and FPGA-style ROM.
//   - For ASIC, IMEM would be replaced by a real ROM or instruction cache.
//
// File Format for $readmemh:
//   Each line should contain ONE 32-bit instruction in HEX.
//   Example (program.hex):
//      00000013   // NOP  (addi x0, x0, 0)
//      00100093   // addi x1, x0, 1
//
// Revision History:
//   - 13-Feb-2026 : Initial version
//=====================================================================

module imem #(
    parameter MEM_DEPTH_WORDS = 1024,                  // Total words in IMEM
    parameter MEM_INIT_FILE   = "program.hex"          // HEX file for initialization
)(
    input  wire [31:0] addr,                           // Byte address from PC
    output wire [31:0] instr                           // 32-bit instruction output
);

    //=================================================================
    // Instruction Memory Storage
    //=================================================================
    // Each entry is one 32-bit RISC-V instruction word.
    // MEM_DEPTH_WORDS = number of 32-bit words.
    //=================================================================
    reg [31:0] mem [0:MEM_DEPTH_WORDS-1];

    //=================================================================
    // Memory Initialization
    //=================================================================
    // Loads instruction words from a hex file at simulation start.
    // If file is missing, IMEM will contain X/unknown values.
    //=================================================================
    initial begin
        $readmemh(MEM_INIT_FILE, mem);
    end

    //=================================================================
    // Address Mapping (Word Addressing)
    //=================================================================
    // RISC-V instructions are 4-byte aligned.
    // So:
    //   PC = byte address
    //   Index = PC / 4 = PC[31:2]
    //=================================================================
    wire [$clog2(MEM_DEPTH_WORDS)-1:0] word_index;
    assign word_index = addr[31:2];

    //=================================================================
    // Combinational Read Output
    //=================================================================
    // Reads instruction directly from memory.
    // No clock required (ROM-like).
    //=================================================================
    assign instr = mem[word_index];

endmodule

RTL_Verification/tb_imem_program_1.v
//=====================================================================
// File        : tb_imem_program_1.v
// Author      : Prabhat Pandey
// Created On  : 25-Feb-2026
// Project     : RV32I Single-Cycle 32-bit RISC-V Processor
// Testbench   : tb_imem_program_1
// Description :
//   Fully self-checking testbench for imem.v using program_1.hex
//
//   This testbench verifies:
//     1) Instruction memory reads correct 32-bit words
//     2) Addressing is word-based (addr[31:2])
//     3) Multiple sequential fetches return expected values
//
// Verification Features:
//   - Fully self-checking
//   - Input print for each test
//   - Expected output print
//   - Actual output print
//   - PASS/FAIL per test case
//   - Global counters for total/pass/fail
//   - Final verification summary report
//
// Run Commands:
//   iverilog -o ./Verification_Results/result_tb_imem_program_1 \
//       ./src/imem.v ./RTL_Verification/tb_imem_program_1.v
//
//   vvp ./Verification_Results/result_tb_imem_program_1
//
// IMPORTANT:
//   This testbench loads program_1.hex into DUT memory (simulation-only).
//   Ensure program_1.hex is present in the simulation working directory.
//=====================================================================

`timescale 1ns/1ps

module tb_imem_program_1;

    //=============================================================
    // Testbench Parameters
    //=============================================================
    localparam integer TEST_DELAY = 10; // ns between tests for waveform visibility

    //=============================================================
    // DUT Signals
    //=============================================================
    reg  [31:0] addr;
    wire [31:0] instr;

    //=============================================================
    // Instantiate DUT
    //=============================================================
    imem #(
        .MEM_DEPTH_WORDS(1024)
    ) dut (
        .addr  (addr),
        .instr (instr)
    );

    //=============================================================
    // Global Verification Counters
    //=============================================================
    integer total_tests;
    integer passed_tests;
    integer failed_tests;

    //=============================================================
    // VCD Dump (for GTKWave)
    //=============================================================
    initial begin
        $dumpfile("tb_imem_program_1.vcd");
        $dumpvars(0, tb_imem_program_1);
    end

    //=============================================================
    // Task: Divider
    //=============================================================
    task print_divider;
        begin
            $display("----------------------------------------------------------------");
        end
    endtask

    //=============================================================
    // Task: Run a Single IMEM Read Test
    //=============================================================
    // Inputs:
    //   test_name      : string name of the test
    //   addr_in        : byte address applied to IMEM
    //   expected_instr : expected 32-bit instruction output
    //
    // Behavior:
    //   - Applies addr
    //   - Waits small time for combinational propagation
    //   - Checks instr
    //   - Prints PASS/FAIL
    //=============================================================
    task run_test;
        input [8*60:1] test_name;
        input [31:0]   addr_in;
        input [31:0]   expected_instr;

        reg [31:0] got_instr;
        begin
            total_tests = total_tests + 1;

            print_divider();
            $display("TEST : %s", test_name);

            // Apply input address
            addr = addr_in;

            // Wait for combinational output to settle
            #2;
            got_instr = instr;

            // Print Inputs
            $display("Inputs:");
            $display("   addr (byte) = %08h", addr_in);
            $display("   addr[31:2]  = %08h", addr_in >> 2);

            // Print Expected
            $display("");
            $display("Expected:");
            $display("   instr       = %08h", expected_instr);

            // Print Got
            $display("");
            $display("Got:");
            $display("   instr       = %08h", got_instr);

            // Compare
            if (got_instr === expected_instr) begin
                passed_tests = passed_tests + 1;
                $display("STATUS: PASS");
            end
            else begin
                failed_tests = failed_tests + 1;
                $display("STATUS: FAIL");
            end

            print_divider();
            $display("");

            #(TEST_DELAY);
        end
    endtask

    //=============================================================
    // Main Test Sequence
    //=============================================================
    initial begin

        // Init counters
        total_tests  = 0;
        passed_tests = 0;
        failed_tests = 0;

        // Init inputs
        addr = 32'h0000_0000;

        // Load program into IMEM (simulation-only)
        $readmemh("program_1.hex", dut.mem);

        $display("====================================================");
        $display(" IMEM VERIFICATION STARTED — Author: Prabhat Pandey");
        $display("====================================================");
        $display("");

        // ----------------------------------------------------------
        // program_1.hex reference:
        // Index 0 : 00000013
        // Index 1 : 00100093
        // Index 2 : 00200113
        // Index 3 : 00308193
        // Index 4 : 00410213
        // ...
        // ----------------------------------------------------------

        // Basic sequential fetch tests
        run_test("Fetch word 0 (PC=0x00000000)", 32'h0000_0000, 32'h0000_0013);
        run_test("Fetch word 1 (PC=0x00000004)", 32'h0000_0004, 32'h0010_0093);
        run_test("Fetch word 2 (PC=0x00000008)", 32'h0000_0008, 32'h0020_0113);
        run_test("Fetch word 3 (PC=0x0000000C)", 32'h0000_000C, 32'h0030_8193);
        run_test("Fetch word 4 (PC=0x00000010)", 32'h0000_0010, 32'h0041_0213);

        // Test: word addressing behavior
        // PC=0x00000005 should still index word 1 because addr[31:2] = 1
        // (In real CPU PC won't be unaligned, but we verify indexing logic)
        run_test("Unaligned addr test (0x00000005 -> word 1)", 32'h0000_0005, 32'h0010_0093);

        // Test: higher addresses
        run_test("Fetch word 10 (PC=0x00000028)", 32'h0000_0028, 32'h00a4_0513);
        run_test("Fetch word 15 (PC=0x0000003C)", 32'h0000_003C, 32'h00f6_8793);

        //=========================================================
        // Final Summary Report
        //=========================================================
        $display("====================================================");
        $display(" IMEM VERIFICATION REPORT");
        $display("====================================================");
        $display("   Total Tests   : %0d", total_tests);
        $display("   Passed        : %0d", passed_tests);
        $display("   Failed        : %0d", failed_tests);
        $display("====================================================");

        if (failed_tests == 0) begin
            $display("STATUS: ALL TESTS PASSED");
        end
        else begin
            $display("STATUS: SOME TESTS FAILED");
        end

        $display("====================================================");
        $display("");

        $finish;
    end

endmodule

Verification_Results/tb_imem_program_1.vcd
$date
	Wed Feb 25 22:41:49 2026
$end
$version
	Icarus Verilog
$end
$timescale
	1ps
$end
$scope module tb_imem_program_1 $end
$var wire 32 ! instr [31:0] $end
$var parameter 32 " TEST_DELAY $end
$var reg 32 # addr [31:0] $end
$var integer 32 $ failed_tests [31:0] $end
$var integer 32 % passed_tests [31:0] $end
$var integer 32 & total_tests [31:0] $end
$scope module dut $end
$var wire 32 ' addr [31:0] $end
$var wire 32 ( instr [31:0] $end
$var wire 10 ) word_index [9:0] $end
$var parameter 32 * MEM_DEPTH_WORDS $end
$upscope $end
$scope task print_divider $end
$upscope $end
$scope task run_test $end
$var reg 32 + addr_in [31:0] $end
$var reg 32 , expected_instr [31:0] $end
$var reg 32 - got_instr [31:0] $end
$var reg 480 . test_name [480:1] $end
$upscope $end
$upscope $end
$enddefinitions $end
$comment Show the parameter values. $end
$dumpall
b10000000000 *
b1010 "
$end
#0
$dumpvars
b1000110011001010111010001100011011010000010000001110111011011110111001001100100001000000011000000100000001010000101000001000011001111010011000001111000001100000011000000110000001100000011000000110000001100000011000000101001 .
bx -
b10011 ,
b0 +
b0 )
b10011 (
b0 '
b1 &
b0 %
b0 $
b0 #
b10011 !
$end
#2000
b1 %
b10011 -
#12000
b100000000000010010011 !
b100000000000010010011 (
b1 )
b100 #
b100 '
b10 &
b100000000000010010011 ,
b100 +
b1000110011001010111010001100011011010000010000001110111011011110111001001100100001000000011000100100000001010000101000001000011001111010011000001111000001100000011000000110000001100000011000000110000001100000011010000101001 .
#14000
b10 %
b100000000000010010011 -
#24000
b1000000000000100010011 !
b1000000000000100010011 (
b10 )
b1000 #
b1000 '
b11 &
b1000000000000100010011 ,
b1000 +
b1000110011001010111010001100011011010000010000001110111011011110111001001100100001000000011001000100000001010000101000001000011001111010011000001111000001100000011000000110000001100000011000000110000001100000011100000101001 .
#26000
b11 %
b1000000000000100010011 -
#36000
b1100001000000110010011 !
b1100001000000110010011 (
b11 )
b1100 #
b1100 '
b100 &
b1100001000000110010011 ,
b1100 +
b1000110011001010111010001100011011010000010000001110111011011110111001001100100001000000011001100100000001010000101000001000011001111010011000001111000001100000011000000110000001100000011000000110000001100000100001100101001 .
#38000
b100 %
b1100001000000110010011 -
#48000
b10000010000001000010011 !
b10000010000001000010011 (
b100 )
b10000 #
b10000 '
b101 &
b10000010000001000010011 ,
b10000 +
b1000110011001010111010001100011011010000010000001110111011011110111001001100100001000000011010000100000001010000101000001000011001111010011000001111000001100000011000000110000001100000011000000110000001100010011000000101001 .
#50000
b101 %
b10000010000001000010011 -
#60000
b100000000000010010011 !
b100000000000010010011 (
b1 )
b101 #
b101 '
b110 &
b100000000000010010011 ,
b101 +
b10101010110111001100001011011000110100101100111011011100110010101100100001000000110000101100100011001000111001000100000011101000110010101110011011101000010000000101000001100000111100000110000001100000011000000110000001100000011000000110000001101010010000000101101001111100010000001110111011011110111001001100100001000000011000100101001 .
#62000
b110 %
b100000000000010010011 -
#72000
b101001000000010100010011 !
b101001000000010100010011 (
b1010 )
b101000 #
b101000 '
b111 &
b101001000000010100010011 ,
b101000 +
b100011001100101011101000110001101101000001000000111011101101111011100100110010000100000001100010011000000100000001010000101000001000011001111010011000001111000001100000011000000110000001100000011000000110000001100100011100000101001 .
#74000
b111 %
b101001000000010100010011 -
#84000
b111101101000011110010011 !
b111101101000011110010011 (
b1111 )
b111100 #
b111100 '
b1000 &
b111101101000011110010011 ,
b111100 +
b100011001100101011101000110001101101000001000000111011101101111011100100110010000100000001100010011010100100000001010000101000001000011001111010011000001111000001100000011000000110000001100000011000000110000001100110100001100101001 .
#86000
b1000 %
b111101101000011110010011 -
