src/pc_reg.v
//=====================================================================
// File        : pc_reg.v
// Author      : Prabhat Pandey
// Created On  : 12-Feb-2026
// Project     : RV32I Single-Cycle 32-bit RISC-V Processor
// Module Name : pc_reg
// Description :
//   This module implements the Program Counter (PC) register for a
//   single-cycle RV32 processor.
//
//   The PC holds the address of the instruction currently being fetched
//   from instruction memory.
//
//   On every rising edge of the clock:
//     - If reset is asserted (active-low), PC is cleared to 0x00000000.
//     - Otherwise, PC is updated with pc_next.
//
// Notes:
//   - RISC-V instructions are always 32-bit aligned, so PC should normally
//     be word-aligned (PC[1:0] = 2'b00).
//   - This module intentionally does NOT force alignment internally,
//     because alignment should be guaranteed by pc_next_logic.
//     (This avoids masking bugs during debugging.)
//
// Revision History:
//   - 12-Feb-2026 : Initial version
//=====================================================================

module pc_reg (
    input  wire        clk,        // Clock input (positive-edge triggered)
    input  wire        rst_n,      // Active-low asynchronous reset
    input  wire [31:0] pc_next,    // Next PC value computed by pc_next_logic
    output reg  [31:0] pc_current  // Current PC value used for instruction fetch
);

    //=================================================================
    // Sequential Logic: Program Counter Update
    //=================================================================
    // Triggering:
    //   - Updates on rising edge of clk
    //   - Resets immediately on falling edge of rst_n
    //
    // Reset Behavior:
    //   - PC is reset to 0x00000000
    //
    // Normal Operation:
    //   - PC loads pc_next every cycle
    //=================================================================
    always @(posedge clk or negedge rst_n) begin
        if (!rst_n) begin
            pc_current <= 32'h0000_0000;   // Reset PC to address 0
        end
        else begin
            pc_current <= pc_next;         // Update PC with computed next value
        end
    end

endmodule

RTL_Verification/tb_pc_reg.v
//=====================================================================
// File        : tb_pc_reg.v
// Author      : Prabhat Pandey
// Created On  : 13-Feb-2026
// Project     : RV32I Single-Cycle 32-bit RISC-V Processor
// Testbench   : tb_pc_reg
// Description :
//   Self-checking testbench for pc_reg.v
//
//   This testbench verifies:
//     1) Reset behavior (PC resets to 0)
//     2) PC update on clock rising edge
//     3) Multiple sequential PC updates
//     4) Reset asserted in the middle of operation
//
// Verification Features:
//   - Fully self-checking
//   - Input print for each test
//   - Expected output print
//   - Actual output print
//   - PASS/FAIL per test case
//   - Global counters for total/pass/fail
//   - Final verification summary report
//
// Run Commands:
//   iverilog -o ./Verification_Results/result_tb_pc_reg ./src/pc_reg.v ./RTL_Verification/tb_pc_reg.v
//   vvp ./Verification_Results/result_tb_pc_reg
//
//=====================================================================

`timescale 1ns/1ps

module tb_pc_reg;

    //=============================================================
    // Testbench Parameters
    //=============================================================
    localparam integer TEST_DELAY = 10; // ns between tests for waveform visibility

    //=============================================================
    // DUT Signals
    //=============================================================
    reg         clk;
    reg         rst_n;
    reg  [31:0] pc_next;
    wire [31:0] pc_current;

    //=============================================================
    // Instantiate DUT (Device Under Test)
    //=============================================================
    pc_reg dut (
        .clk        (clk),
        .rst_n      (rst_n),
        .pc_next    (pc_next),
        .pc_current (pc_current)
    );

    //=============================================================
    // Global Verification Counters
    //=============================================================
    integer total_tests;
    integer passed_tests;
    integer failed_tests;

    //=============================================================
    // VCD Dump (for GTKWave)
    //=============================================================
    initial begin
        $dumpfile("tb_pc_reg.vcd");
        $dumpvars(0, tb_pc_reg);
    end

    //=============================================================
    // Clock Generation (10ns period)
    //=============================================================
    initial begin
        clk = 1'b0;
        forever #5 clk = ~clk;
    end

    //=============================================================
    // Task: Print Test Header Divider
    //=============================================================
    task print_divider;
        begin
            $display("----------------------------------------------------------------");
        end
    endtask

    //=============================================================
    // Task: Run a Single Test
    //=============================================================
    // Inputs:
    //   test_name     : string name of the test
    //   next_val      : value to apply to pc_next
    //   expected_pc   : expected value at pc_current AFTER posedge
    //   apply_reset   : 1 = assert reset before checking, 0 = normal
    //
    // Behavior:
    //   - Optionally asserts reset
    //   - Applies pc_next
    //   - Waits for posedge clk
    //   - Checks pc_current against expected
    //   - Prints PASS/FAIL
    //=============================================================
    task run_test;
        input [8*60:1] test_name;     // up to 60 chars
        input [31:0]   next_val;
        input [31:0]   expected_pc;
        input          apply_reset;

        reg [31:0] got_pc;
        begin
            total_tests = total_tests + 1;

            print_divider();
            $display("TEST : %s", test_name);

            // Optional reset assertion
            if (apply_reset) begin
                rst_n = 1'b0;
            end

            // Apply input
            pc_next = next_val;

            // Show Inputs
            $display("Inputs:");
            $display("   rst_n      = %0d", rst_n);
            $display("   pc_next    = %08h", pc_next);

            // Wait for rising edge so PC updates
            @(posedge clk);
            #1; // small delay to allow pc_current to settle

            got_pc = pc_current;

            // Print Expected vs Got
            $display("");
            $display("Expected:");
            $display("   pc_current = %08h", expected_pc);

            $display("");
            $display("Got:");
            $display("   pc_current = %08h", got_pc);

            // Compare
            if (got_pc === expected_pc) begin
                passed_tests = passed_tests + 1;
                $display("STATUS: PASS");
            end
            else begin
                failed_tests = failed_tests + 1;
                $display("STATUS: FAIL");
            end

            print_divider();
            $display("");

            // Deassert reset after test if it was applied
            if (apply_reset) begin
                rst_n = 1'b1;
            end

            #(TEST_DELAY);
        end
    endtask

    //=============================================================
    // Main Test Sequence
    //=============================================================
    initial begin

        // Init counters
        total_tests  = 0;
        passed_tests = 0;
        failed_tests = 0;

        // Init inputs
        rst_n   = 1'b0;
        pc_next = 32'h0000_0000;

        $display("====================================================");
        $display(" PC_REG VERIFICATION STARTED — Author: Prabhat Pandey");
        $display("====================================================");
        $display("");

        // ---------------------------------------------------------
        // TEST 1: Reset forces PC to 0
        // ---------------------------------------------------------
        // During reset, PC should become 0 on the next posedge.
        run_test("RESET behavior (PC must go to 0)", 32'hDEAD_BEEF, 32'h0000_0000, 1'b1);

        // ---------------------------------------------------------
        // TEST 2: Normal PC update after reset release
        // ---------------------------------------------------------
        // After reset is released, PC should load pc_next.
        run_test("PC update basic (load 0x00000004)", 32'h0000_0004, 32'h0000_0004, 1'b0);

        // ---------------------------------------------------------
        // TEST 3: Sequential update (multiple cycles)
        // ---------------------------------------------------------
        run_test("Sequential update (load 0x00000008)", 32'h0000_0008, 32'h0000_0008, 1'b0);
        run_test("Sequential update (load 0x0000000C)", 32'h0000_000C, 32'h0000_000C, 1'b0);

        // ---------------------------------------------------------
        // TEST 4: Large address update
        // ---------------------------------------------------------
        run_test("Large PC value (load 0x80000000)", 32'h8000_0000, 32'h8000_0000, 1'b0);

        // ---------------------------------------------------------
        // TEST 5: Reset asserted mid-run
        // ---------------------------------------------------------
        // Force reset again and verify PC becomes 0.
        run_test("Mid-run reset (PC must return to 0)", 32'h1234_5678, 32'h0000_0000, 1'b1);

        // ---------------------------------------------------------
        // TEST 6: Update after mid-run reset
        // ---------------------------------------------------------
        run_test("Post-reset update (load 0x00000100)", 32'h0000_0100, 32'h0000_0100, 1'b0);

        //=========================================================
        // Final Summary Report
        //=========================================================
        $display("====================================================");
        $display(" PC_REG VERIFICATION REPORT");
        $display("====================================================");
        $display("   Total Tests   : %0d", total_tests);
        $display("   Passed        : %0d", passed_tests);
        $display("   Failed        : %0d", failed_tests);
        $display("====================================================");

        if (failed_tests == 0) begin
            $display("STATUS: ALL TESTS PASSED");
        end
        else begin
            $display("STATUS: SOME TESTS FAILED");
        end

        $display("====================================================");
        $display("");

        $finish;
    end

endmodule

Verification_Results/tb_pc_reg.vcd
$date
	Wed Feb 25 22:41:50 2026
$end
$version
	Icarus Verilog
$end
$timescale
	1ps
$end
$scope module tb_pc_reg $end
$var wire 32 ! pc_current [31:0] $end
$var parameter 32 " TEST_DELAY $end
$var reg 1 # clk $end
$var reg 32 $ pc_next [31:0] $end
$var reg 1 % rst_n $end
$var integer 32 & failed_tests [31:0] $end
$var integer 32 ' passed_tests [31:0] $end
$var integer 32 ( total_tests [31:0] $end
$scope module dut $end
$var wire 1 # clk $end
$var wire 32 ) pc_next [31:0] $end
$var wire 1 % rst_n $end
$var reg 32 * pc_current [31:0] $end
$upscope $end
$scope task print_divider $end
$upscope $end
$scope task run_test $end
$var reg 1 + apply_reset $end
$var reg 32 , expected_pc [31:0] $end
$var reg 32 - got_pc [31:0] $end
$var reg 32 . next_val [31:0] $end
$var reg 480 / test_name [480:1] $end
$upscope $end
$upscope $end
$enddefinitions $end
$comment Show the parameter values. $end
$dumpall
b1010 "
$end
#0
$dumpvars
b101001001000101010100110100010101010100001000000110001001100101011010000110000101110110011010010110111101110010001000000010100001010000010000110010000001101101011101010111001101110100001000000110011101101111001000000111010001101111001000000011000000101001 /
b11011110101011011011111011101111 .
bx -
b0 ,
1+
bx *
b11011110101011011011111011101111 )
b1 (
b0 '
b0 &
0%
b11011110101011011011111011101111 $
0#
bx !
$end
#5000
b0 !
b0 *
1#
#6000
1%
b1 '
b0 -
#10000
0#
#15000
b11011110101011011011111011101111 !
b11011110101011011011111011101111 *
1#
#16000
b100 $
b100 )
b10 (
0+
b100 ,
b100 .
b10100000100001100100000011101010111000001100100011000010111010001100101001000000110001001100001011100110110100101100011001000000010100001101100011011110110000101100100001000000011000001111000001100000011000000110000001100000011000000110000001100000011010000101001 /
#20000
0#
#25000
b100 !
b100 *
1#
#26000
b10 '
b100 -
#30000
0#
#35000
1#
#36000
b1000 $
b1000 )
b11 (
b1000 ,
b1000 .
b101001101100101011100010111010101100101011011100111010001101001011000010110110000100000011101010111000001100100011000010111010001100101001000000010100001101100011011110110000101100100001000000011000001111000001100000011000000110000001100000011000000110000001100000011100000101001 /
#40000
0#
#45000
b1000 !
b1000 *
1#
#46000
b11 '
b1000 -
#50000
0#
#55000
1#
#56000
b1100 $
b1100 )
b100 (
b1100 ,
b1100 .
b101001101100101011100010111010101100101011011100111010001101001011000010110110000100000011101010111000001100100011000010111010001100101001000000010100001101100011011110110000101100100001000000011000001111000001100000011000000110000001100000011000000110000001100000100001100101001 /
#60000
0#
#65000
b1100 !
b1100 *
1#
#66000
b100 '
b1100 -
#70000
0#
#75000
1#
#76000
b10000000000000000000000000000000 $
b10000000000000000000000000000000 )
b101 (
b10000000000000000000000000000000 ,
b10000000000000000000000000000000 .
b100110001100001011100100110011101100101001000000101000001000011001000000111011001100001011011000111010101100101001000000010100001101100011011110110000101100100001000000011000001111000001110000011000000110000001100000011000000110000001100000011000000101001 /
#80000
0#
#85000
b10000000000000000000000000000000 !
b10000000000000000000000000000000 *
1#
#86000
b101 '
b10000000000000000000000000000000 -
#90000
0#
#95000
1#
#96000
b10010001101000101011001111000 $
b10010001101000101011001111000 )
0%
b110 (
1+
b0 ,
b10010001101000101011001111000 .
b100110101101001011001000010110101110010011101010110111000100000011100100110010101110011011001010111010000100000001010000101000001000011001000000110110101110101011100110111010000100000011100100110010101110100011101010111001001101110001000000111010001101111001000000011000000101001 /
#100000
0#
#105000
b0 !
b0 *
1#
#106000
1%
b110 '
b0 -
#110000
0#
#115000
b10010001101000101011001111000 !
b10010001101000101011001111000 *
1#
#116000
b100000000 $
b100000000 )
b111 (
0+
b100000000 ,
b100000000 .
b101000001101111011100110111010000101101011100100110010101110011011001010111010000100000011101010111000001100100011000010111010001100101001000000010100001101100011011110110000101100100001000000011000001111000001100000011000000110000001100000011000000110001001100000011000000101001 /
#120000
0#
#125000
b100000000 !
b100000000 *
1#
#126000
b111 '
b100000000 -
